Workbook

Sheet Read Me
A1: Combat Balance Workbook
A2: v0.1 • Draft • единый источник настраиваемых чисел для Combat Lab
A4: Паспорт документа | F4: Контроль качества | K4: Профиль бойцов
A5: Поле | B5: Значение | C5: Статус | D5: Примечание | F5: Метрика | G5: Текущее | H5: Требование | I5: Статус | K5: Параметр | L5: Медведь | M5: Кенгуру | N5: Горилла
A6: Документ | B6: Combat Balance Workbook | C6: Draft | D6: Числовое приложение к CDS v0.1 | F6: Животные | G6: =COUNTA('Fighter Stats'!$A$6:$A$8) -> 3 | H6: 3 | I6: =IF(G6=H6,"OK","ERROR") -> OK | K6: Health | L6: ='Fighter Stats'!D6 -> 1650 | M6: ='Fighter Stats'!D7 -> 1150 | N6: ='Fighter Stats'!D8 -> 1450
A7: Версия | B7: v0.1 | C7: Hypothesis | D7: До пакетных симуляций | F7: Действия | G7: =COUNTA(Actions!$A$6:$A$29) -> 24 | H7: 24 | I7: =IF(G7=H7,"OK","ERROR") -> OK | K7: Power | L7: ='Fighter Stats'!E6 -> 130 | M7: ='Fighter Stats'!E7 -> 100 | N7: ='Fighter Stats'!E8 -> 110
A8: Обновлено | B8: 46232 | C8: Current | D8: Europe/Warsaw | F8: Пассивы | G8: =COUNTA(Passives!$A$6:$A$11) -> 6 | H8: 6 | I8: =IF(G8=H8,"OK","ERROR") -> OK | K8: Armor | L8: ='Fighter Stats'!F6 -> 75 | M8: ='Fighter Stats'!F7 -> 40 | N8: ='Fighter Stats'!F8 -> 95
A9: Владелец | B9: Game Designer / Founder / Product Owner | C9: Assigned | D9: Один владелец решения | F9: Эффекты | G9: =COUNTA(Effects!$A$6:$A$15) -> 10 | H9: 10 | I9: =IF(G9=H9,"OK","ERROR") -> OK | K9: Move Speed | L9: ='Fighter Stats'!K6 -> 70 | M9: ='Fighter Stats'!K7 -> 135 | N9: ='Fighter Stats'!K8 -> 75
A10: Источник правил | B10: Combat Design Specification v0.1 | C10: Linked | D10: Формулы и семантика — в CDS | F10: Тактики | G10: =COUNTA(Tactics!$A$6:$A$9) -> 4 | H10: 4 | I10: =IF(G10=H10,"OK","ERROR") -> OK
A11: Целевой бой | B11: 35–60 секунд | C11: Target | D11: Timeout менее 2% | F11: Экипировка | G11: =COUNTA(Gear!$A$6:$A$14) -> 9 | H11: 9 | I11: =IF(G11=H11,"OK","ERROR") -> OK | K11: JSON map SHA-256: 9b5c4aae4551d2f61ea3d02d4121898e09c0ad333ca4714b112a4124f1e6aebf
A12: JSON schema | B12: combat.balance/0.1 | C12: Mapped | D12: Лист JSON Map | F12: Тестовые сборки | G12: =COUNTA('Test Builds'!$A$6:$A$17) -> 12 | H12: 12 | I12: =IF(G12=H12,"OK","ERROR") -> OK
A13: Числа в коде/CDS | B13: Запрещены | C13: Fixed | D13: Только технические инварианты формата | F13: Matchup rows | G13: =COUNTA('Expected Matchups'!$A$6:$A$14) -> 9 | H13: 9 | I13: =IF(G13=H13,"OK","ERROR") -> OK
F14: Ошибки валидации | G14: =COUNTIF(Validation!$E$6:$E$166,"ERROR") -> 0 | H14: 0 | I14: =IF(G14=H14,"OK","ERROR") -> OK
A16: Как работать с книгой
A17: Шаг | B17: Действие | C17: Результат | D17: Блокирующая проверка
A18: 1 | B18: Менять только жёлтые входные клетки на профильном листе. | C18: Validation пересчитывается. | D18: Нет ERROR.
A19: 2 | B19: Добавить запись в Change Log и повысить ConfigVersion. | C19: Изменение трассируется. | D19: Версия уникальна.
A20: 3 | B20: Экспортировать JSON по живой карте JSON Map. | C20: Сортированный canonical JSON. | D20: ValueType и Required соблюдены.
A21: 4 | B21: Запустить seed sweep и вставить агрегаты в Batch Results. | C21: Получены статистические распределения. | D21: DeterminismFailures = 0.
A22: 5 | B22: Сравнить с Expected Matchups и принять balance pass. | C22: PASS или осознанное изменение гипотезы. | D22: Timeout < 2%; длительность 35–60 s.
A24: Легенда и ключевые ограничения
A25: Цвет | B25: Смысл | C25: Ограничение
A26: Жёлтый | B26: Настраиваемый input | C26: Единственное место изменения числа.
A27: Голубой | B27: Stable ID / ключ | C27: Семантика ID не меняется без новой схемы.
A28: Зелёный | B28: Формула / проверка | C28: Не заменять статическим значением.
A29: Красный | B29: Ошибка | C29: JSON export и batch approval запрещены.

Sheet Global Config
A1: Global Config
A2: Глобальные коэффициенты, пределы, тайминги и ресурсные профили
A3: Жёлтые клетки — настраиваемые данные. Зелёные — вычисляемая проверка диапазона. Любое изменение требует новой ConfigVersion и записи в Change Log.
A5: Key | B5: Group | C5: Description RU | D5: Value | E5: Data Type | F5: Unit | G5: Min | H5: Max | I5: Status | J5: Notes RU | K5: Validation
A6: global.sim.schema_version | B6: Simulation | C6: Версия схемы баланса | D6: combat.balance/0.2 | E6: string | F6: id | I6: Fixed | J6: Менять только вместе со схемой JSON. | K6: =IF(OR(E6="string",E6="bool",AND(D6>=G6,D6<=H6)),"OK","ERROR") -> OK
A7: global.sim.config_version | B7: Simulation | C7: Версия набора параметров | D7: v0.2 | E7: string | F7: id | I7: Hypothesis | J7: Повышается при любом утверждённом balance pass. | K7: =IF(OR(E7="string",E7="bool",AND(D7>=G7,D7<=H7)),"OK","ERROR") -> OK
A8: global.sim.rng_version | B8: Simulation | C8: Версия алгоритма RNG | D8: pcg32/1 | E8: string | F8: id | I8: Hypothesis | J8: Финально фиксируется в Combat Lab Technical Design. | K8: =IF(OR(E8="string",E8="bool",AND(D8>=G8,D8<=H8)),"OK","ERROR") -> OK
A9: global.sim.ordering_version | B9: Simulation | C9: Версия порядка тика | D9: tick-pipeline/1 | E9: string | F9: id | I9: Fixed | J9: Соответствует CDS v0.1, раздел 4.2. | K9: =IF(OR(E9="string",E9="bool",AND(D9>=G9,D9<=H9)),"OK","ERROR") -> OK
A10: global.sim.tick_ms | B10: Simulation | C10: Длительность одного тика | D10: 100 | E10: int | F10: ms | G10: 50 | H10: 200 | I10: Hypothesis | J10: 10 тиков в секунду; все фазы целочисленные. | K10: =IF(OR(E10="string",E10="bool",AND(D10>=G10,D10<=H10)),"OK","ERROR") -> OK
A11: battle.time_limit_ticks | B11: Simulation | C11: Лимит боя | D11: 600 | E11: int | F11: ticks | G11: 350 | H11: 900 | I11: Hypothesis | J11: 60 секунд при tick_ms=100. | K11: =IF(OR(E11="string",E11="bool",AND(D11>=G11,D11<=H11)),"OK","ERROR") -> OK
A12: global.sim.fp_scale | B12: Math | C12: Масштаб fixed-point | D12: 1000 | E12: int | F12: fp | G12: 100 | H12: 100000 | I12: Fixed | J12: 1000 = множитель 1.000 и вероятность 100%. | K12: =IF(OR(E12="string",E12="bool",AND(D12>=G12,D12<=H12)),"OK","ERROR") -> OK
A13: global.sim.probability_min | B13: Math | C13: Минимум вероятности | D13: 0 | E13: fp | F13: fp | G13: 0 | H13: 0 | I13: Fixed | J13: Нижняя граница clamp. | K13: =IF(OR(E13="string",E13="bool",AND(D13>=G13,D13<=H13)),"OK","ERROR") -> OK
A14: global.sim.probability_max | B14: Math | C14: Максимум вероятности | D14: 1000 | E14: fp | F14: fp | G14: 1000 | H14: 1000 | I14: Fixed | J14: Верхняя граница clamp. | K14: =IF(OR(E14="string",E14="bool",AND(D14>=G14,D14<=H14)),"OK","ERROR") -> OK
A15: global.sim.multiplier_min | B15: Math | C15: Минимальный множитель веса | D15: 250 | E15: fp | F15: fp | G15: 0 | H15: 1000 | I15: Hypothesis | J15: 0.250x. | K15: =IF(OR(E15="string",E15="bool",AND(D15>=G15,D15<=H15)),"OK","ERROR") -> OK
A16: global.sim.multiplier_max | B16: Math | C16: Максимальный множитель веса | D16: 3000 | E16: fp | F16: fp | G16: 1000 | H16: 5000 | I16: Hypothesis | J16: 3.000x. | K16: =IF(OR(E16="string",E16="bool",AND(D16>=G16,D16<=H16)),"OK","ERROR") -> OK
A17: global.sim.decision_weight_max | B17: Math | C17: Максимальный итоговый вес | D17: 100000000 | E17: int | F17: weight | G17: 1000000 | H17: 2000000000 | I17: Hypothesis | J17: Ограничивает переполнение суммы весов. | K17: =IF(OR(E17="string",E17="bool",AND(D17>=G17,D17<=H17)),"OK","ERROR") -> OK
A18: global.arena.min_position | B18: Arena | C18: Левая граница арены | D18: 0 | E18: int | F18: position | G18: 0 | H18: 0 | I18: Hypothesis | J18: Закрытый одномерный отрезок. | K18: =IF(OR(E18="string",E18="bool",AND(D18>=G18,D18<=H18)),"OK","ERROR") -> OK
A19: global.arena.max_position | B19: Arena | C19: Правая граница арены | D19: 10000 | E19: int | F19: position | G19: 6000 | H19: 20000 | I19: Hypothesis | J19: Рабочая длина 10 000 условных единиц. | K19: =IF(OR(E19="string",E19="bool",AND(D19>=G19,D19<=H19)),"OK","ERROR") -> OK
A20: global.arena.start_position_a | B20: Arena | C20: Стартовая позиция A | D20: 2000 | E20: int | F20: position | G20: 500 | H20: 4500 | I20: Hypothesis | J20: Зеркальна позиции B. | K20: =IF(OR(E20="string",E20="bool",AND(D20>=G20,D20<=H20)),"OK","ERROR") -> OK
A21: global.arena.start_position_b | B21: Arena | C21: Стартовая позиция B | D21: 8000 | E21: int | F21: position | G21: 5500 | H21: 9500 | I21: Hypothesis | J21: Зеркальна позиции A. | K21: =IF(OR(E21="string",E21="bool",AND(D21>=G21,D21<=H21)),"OK","ERROR") -> OK
... A127: global.control.knockdown_getup_ticks | B127: Control | C127: Knockdown: длительность GetUp | D127: 3 | E127: int | F127: ticks | G127: 1 | H127: 100 | I127: FIXED | J127: OPEN-WP10-20; wakeup in phase 2. | K127: =IF(OR(E127="string",E127="bool",AND(D127>=G127,D127<=H127)),"OK","ERROR") -> OK

Sheet Fighter Stats
A1: Fighter Stats
A2: Характеристики стартовых животных и их уникальные ресурсы
A3: Base Combat Index — только грубая аналитическая средняя рейтингов E:P; он не участвует в боевой формуле. Относительная идентичность комплекта важнее одинаковой суммы.
A5: Animal ID | B5: Display Name RU | C5: Resource ID | D5: Max Health | E5: Power | F5: Armor | G5: Precision | H5: Evasion | I5: Guard | J5: Guard Break | K5: Move Speed | L5: Action Speed | M5: Initiative | N5: Control Power | O5: Control Resistance | P5: Mass | Q5: Max Energy | R5: Energy Regen / tick | S5: Collision Radius | T5: Start Resource | U5: Max Resource | V5: Stagger Threshold | W5: Base Combat Index | X5: Archetype RU | Y5: Win Condition RU | Z5: Status | AA5: Validation
A6: bear | B6: Медведь | C6: rage | D6: 1650 | E6: 130 | F6: 75 | G6: 95 | H6: 55 | I6: 105 | J6: 120 | K6: 70 | L6: 85 | M6: 85 | N6: 125 | O6: 125 | P6: 130 | Q6: 1000 | R6: 12 | S6: 520 | T6: 0 | U6: 1000 | V6: 260 | W6: =ROUND(AVERAGE(E6:P6),0) -> 100 | X6: Танк-комбэкер | Y6: Пережить давление, накопить ярость и наказать длинный commit. | Z6: Hypothesis | AA6: =IF(AND(A6<>"",D6>0,Q6>0,R6>=0,T6>=0,T6<=U6,V6>0),"OK","ERROR") -> OK
A7: kangaroo | B7: Кенгуру | C7: tempo | D7: 1150 | E7: 100 | F7: 40 | G7: 125 | H7: 135 | I7: 65 | J7: 80 | K7: 135 | L7: 125 | M7: 130 | N7: 75 | O7: 70 | P7: 70 | Q7: 1000 | R7: 15 | S7: 430 | T7: 0 | U7: 1000 | V7: 180 | W7: =ROUND(AVERAGE(E7:P7),0) -> 96 | X7: Мобильный темповик | Y7: Держать среднюю дистанцию, чередовать категории и реализовать окно. | Z7: Hypothesis | AA7: =IF(AND(A7<>"",D7>0,Q7>0,R7>=0,T7>=0,T7<=U7,V7>0),"OK","ERROR") -> OK
A8: gorilla | B8: Горилла | C8: grip | D8: 1450 | E8: 110 | F8: 95 | G8: 90 | H8: 45 | I8: 140 | J8: 105 | K8: 75 | L8: 105 | M8: 95 | N8: 145 | O8: 130 | P8: 150 | Q8: 1000 | R8: 11 | S8: 550 | T8: 0 | U8: 1000 | V8: 300 | W8: =ROUND(AVERAGE(E8:P8),0) -> 107 | X8: Контроллер стены | Y8: Загнать к стене, накопить хватку и реализовать grab/control. | Z8: Hypothesis | AA8: =IF(AND(A8<>"",D8>0,Q8>0,R8>=0,T8>=0,T8<=U8,V8>0),"OK","ERROR") -> OK

Sheet Actions
A1: Actions & Abilities
A2: Системные действия, 12 базовых действий и 9 особых приёмов
A3: Урон рассчитывается по CDS; аналитические колонки справа показывают один hit без контекстных множителей. HitSchedule — относительные тики активного окна.
A5: Action ID | B5: Animal ID | C5: Display Name RU | D5: Slot Type | E5: Category | F5: Tags | G5: Base Weight | H5: Preferred Range Min | I5: Preferred Range Max | J5: Hit Range Min | K5: Hit Range Max | L5: Energy Cost | M5: Resource Cost | N5: Base Damage / hit | O5: Power Ratio FP | P5: Min Damage | Q5: Chip Min | R5: Startup Base Ticks | S5: Startup Min Ticks | T5: Startup Max Ticks | U5: Active Ticks | V5: Hit Schedule | W5: Hit Count | X5: Recovery Base Ticks | Y5: Recovery Min Ticks | Z5: Recovery Max Ticks | AA5: Cooldown Ticks | AB5: Action Priority | AC5: Clash Priority | AD5: Grab Priority | AE5: Resolution Priority | AF5: Interrupt Profile | AG5: Blockable | AH5: Dodgeable | AI5: Undodgeable | AJ5: Wall Impact | AK5: Track Target | AL5: Block Base Chance FP | AM5: Block Reduction FP | AN5: Dodge Base Chance FP | AO5: Movement Mode | AP5: Move Distance | AQ5: Base Stagger | AR5: Base Stun Ticks | AS5: Base Knockback | AT5: Knockback Min | AU5: Knockback Max | AV5: Wall Damage / Unit FP | AW5: Wall Damage Min | AX5: Wall Damage Max | AY5: Max Consecutive Uses | AZ5: Opportunity Cap FP | BA5: Hard Opportunity Misses | BB5: Expected Power Term | BC5: Expected vs Benchmark Armor | BD5: Status | BE5: Validation | BF5: Notes RU | BG5: Hit Interrupt Strength | BH5: Hit Interrupt Min Strength | BI5: Hit Interruptible Phases | BJ5: Protected Phases | BK5: Ignored Control Categories
A6: sys_approach | B6: all | C6: Системное сближение | D6: System | E6: Movement | F6: system|movement|approach | G6: 650 | H6: 0 | I6: 1500 | J6: 0 | K6: 0 | L6: 0 | M6: 0 | N6: 0 | O6: 0 | P6: 0 | Q6: 0 | R6: 1 | S6: 1 | T6: 1 | U6: 5 | W6: 0 | X6: 1 | Y6: 1 | Z6: 1 | AA6: 0 | AB6: 5 | AC6: 0 | AD6: 0 | AE6: 5 | AF6: Cancelable | AG6: FALSE | AH6: FALSE | AI6: FALSE | AJ6: FALSE | AK6: TRUE | AL6: 0 | AM6: 0 | AN6: 0 | AO6: Approach | AP6: 0 | AQ6: 0 | AR6: 0 | AS6: 0 | AT6: 0 | AU6: 0 | AV6: 0 | AW6: 0 | AX6: 0 | AY6: 4 | AZ6: 1000 | BA6: 0 | BB6: =IF(B6="all",0,N6+ROUND(VLOOKUP(B6,'Fighter Stats'!$A$6:$E$8,5,FALSE)*O6/'Global Config'!$D$12,0)) -> 0 | BC6: =ROUND(BB6*(1-('Global Config'!$D$36/('Global Config'!$D$36+'Global Config'!$D$23))),0) -> 0 | BD6: Hypothesis | BE6: =IF(AND(A6<>"",H6<=I6,J6<=K6,S6<=R6,R6<=T6,Y6<=X6,X6<=Z6,AT6<=AS6,AS6<=AU6,AW6<=AX6,AY6>=1,L6>=0,M6>=0),"OK","ERROR") -> OK | BF6: Движется к preferred band профиля; дистанция берётся из effective MoveSpeed. | BG6: 0 | BH6: 1 | BI6: Startup|Active
A7: sys_retreat | B7: all | C7: Системное отступление | D7: System | E7: Movement | F7: system|movement|retreat | G7: 450 | H7: 1600 | I7: 3000 | J7: 0 | K7: 0 | L7: 0 | M7: 0 | N7: 0 | O7: 0 | P7: 0 | Q7: 0 | R7: 1 | S7: 1 | T7: 1 | U7: 5 | W7: 0 | X7: 1 | Y7: 1 | Z7: 1 | AA7: 0 | AB7: 5 | AC7: 0 | AD7: 0 | AE7: 5 | AF7: Cancelable | AG7: FALSE | AH7: FALSE | AI7: FALSE | AJ7: FALSE | AK7: TRUE | AL7: 0 | AM7: 0 | AN7: 0 | AO7: Retreat | AP7: 0 | AQ7: 0 | AR7: 0 | AS7: 0 | AT7: 0 | AU7: 0 | AV7: 0 | AW7: 0 | AX7: 0 | AY7: 3 | AZ7: 1000 | BA7: 0 | BB7: =IF(B7="all",0,N7+ROUND(VLOOKUP(B7,'Fighter Stats'!$A$6:$E$8,5,FALSE)*O7/'Global Config'!$D$12,0)) -> 0 | BC7: =ROUND(BB7*(1-('Global Config'!$D$36/('Global Config'!$D$36+'Global Config'!$D$23))),0) -> 0 | BD7: Hypothesis | BE7: =IF(AND(A7<>"",H7<=I7,J7<=K7,S7<=R7,R7<=T7,Y7<=X7,X7<=Z7,AT7<=AS7,AS7<=AU7,AW7<=AX7,AY7>=1,L7>=0,M7>=0),"OK","ERROR") -> OK | BF7: Останавливается у стены; не превращает остаток движения в урон. | BG7: 0 | BH7: 1 | BI7: Startup|Active
A8: sys_wait | B8: all | C8: Системное ожидание | D8: System | E8: Wait | F8: system|wait | G8: 150 | H8: 0 | I8: 10000 | J8: 0 | K8: 0 | L8: 0 | M8: 0 | N8: 0 | O8: 0 | P8: 0 | Q8: 0 | R8: 0 | S8: 0 | T8: 0 | U8: 3 | W8: 0 | X8: 0 | Y8: 0 | Z8: 0 | AA8: 0 | AB8: 1 | AC8: 0 | AD8: 0 | AE8: 1 | AF8: Cancelable | AG8: FALSE | AH8: FALSE | AI8: FALSE | AJ8: FALSE | AK8: FALSE | AL8: 0 | AM8: 0 | AN8: 0 | AO8: None | AP8: 0 | AQ8: 0 | AR8: 0 | AS8: 0 | AT8: 0 | AU8: 0 | AV8: 0 | AW8: 0 | AX8: 0 | AY8: 2 | AZ8: 1000 | BA8: 0 | BB8: =IF(B8="all",0,N8+ROUND(VLOOKUP(B8,'Fighter Stats'!$A$6:$E$8,5,FALSE)*O8/'Global Config'!$D$12,0)) -> 0 | BC8: =ROUND(BB8*(1-('Global Config'!$D$36/('Global Config'!$D$36+'Global Config'!$D$23))),0) -> 0 | BD8: Hypothesis | BE8: =IF(AND(A8<>"",H8<=I8,J8<=K8,S8<=R8,R8<=T8,Y8<=X8,X8<=Z8,AT8<=AS8,AS8<=AU8,AW8<=AX8,AY8>=1,L8>=0,M8>=0),"OK","ERROR") -> OK | BF8: Выбирается при нулевых весах или тактически полезной паузе. | BG8: 0 | BH8: 1 | BI8: Startup
A9: bear_paw_jab | B9: bear | C9: Быстрый удар лапой | D9: Basic | E9: LightStrike | F9: strike|light|fallback | G9: 1000 | H9: 100 | I9: 900 | J9: 0 | K9: 1050 | L9: 0 | M9: 0 | N9: 30 | O9: 450 | P9: 12 | Q9: 4 | R9: 3 | S9: 2 | T9: 5 | U9: 1 | V9: 0 | W9: 1 | X9: 5 | Y9: 3 | Z9: 8 | AA9: 0 | AB9: 20 | AC9: 20 | AD9: 0 | AE9: 20 | AF9: Committed | AG9: TRUE | AH9: TRUE | AI9: FALSE | AJ9: FALSE | AK9: FALSE | AL9: 0 | AM9: 0 | AN9: 0 | AO9: None | AP9: 0 | AQ9: 20 | AR9: 0 | AS9: 0 | AT9: 0 | AU9: 0 | AV9: 0 | AW9: 0 | AX9: 0 | AY9: 2 | AZ9: 1000 | BA9: 0 | BB9: =IF(B9="all",0,N9+ROUND(VLOOKUP(B9,'Fighter Stats'!$A$6:$E$8,5,FALSE)*O9/'Global Config'!$D$12,0)) -> 89 | BC9: =ROUND(BB9*(1-('Global Config'!$D$36/('Global Config'!$D$36+'Global Config'!$D$23))),0) -> 59 | BD9: Hypothesis | BE9: =IF(AND(A9<>"",H9<=I9,J9<=K9,S9<=R9,R9<=T9,Y9<=X9,X9<=Z9,AT9<=AS9,AS9<=AU9,AW9<=AX9,AY9>=1,L9>=0,M9>=0),"OK","ERROR") -> OK | BF9: Безопасный fallback; сильный repeat penalty. | BG9: 1 | BH9: 1 | BI9: Startup
A10: bear_crushing_swipe | B10: bear | C10: Сокрушительный взмах | D10: Basic | E10: HeavyStrike | F10: strike|heavy|guard_break|knockback | G10: 720 | H10: 400 | I10: 1350 | J10: 150 | K10: 1700 | L10: 180 | M10: 0 | N10: 60 | O10: 900 | P10: 25 | Q10: 8 | R10: 8 | S10: 5 | T10: 12 | U10: 2 | V10: 0 | W10: 1 | X10: 12 | Y10: 8 | Z10: 18 | AA10: 35 | AB10: 40 | AC10: 45 | AD10: 0 | AE10: 40 | AF10: Armored | AG10: TRUE | AH10: TRUE | AI10: FALSE | AJ10: FALSE | AK10: FALSE | AL10: 0 | AM10: 0 | AN10: 0 | AO10: Push | AP10: 0 | AQ10: 120 | AR10: 4 | AS10: 650 | AT10: 200 | AU10: 900 | AV10: 0 | AW10: 0 | AX10: 0 | AY10: 1 | AZ10: 1200 | BA10: 0 | BB10: =IF(B10="all",0,N10+ROUND(VLOOKUP(B10,'Fighter Stats'!$A$6:$E$8,5,FALSE)*O10/'Global Config'!$D$12,0)) -> 177 | BC10: =ROUND(BB10*(1-('Global Config'!$D$36/('Global Config'!$D$36+'Global Config'!$D$23))),0) -> 118 | BD10: Hypothesis | BE10: =IF(AND(A10<>"",H10<=I10,J10<=K10,S10<=R10,R10<=T10,Y10<=X10,X10<=Z10,AT10<=AS10,AS10<=AU10,AW10<=AX10,AY10>=1,L10>=0,M10>=0),"OK","ERROR") -> OK | BF10: Наказывает Block/Recovery; длинный telegraph и recovery. | BG10: 3 | BH10: 3 | BI10: Startup | BJ10: Startup|Active
A11: bear_guarded_advance | B11: bear | C11: Защищённое наступление | D11: Basic | E11: BlockMovement | F11: movement|approach|block|defense | G11: 650 | H11: 200 | I11: 900 | J11: 0 | K11: 0 | L11: 100 | M11: 0 | N11: 0 | O11: 0 | P11: 0 | Q11: 0 | R11: 3 | S11: 2 | T11: 5 | U11: 10 | W11: 0 | X11: 6 | Y11: 4 | Z11: 9 | AA11: 20 | AB11: 30 | AC11: 0 | AD11: 0 | AE11: 70 | AF11: Armored | AG11: FALSE | AH11: FALSE | AI11: FALSE | AJ11: FALSE | AK11: TRUE | AL11: 550 | AM11: 500 | AN11: 0 | AO11: Approach | AP11: 700 | AQ11: 0 | AR11: 0 | AS11: 0 | AT11: 0 | AU11: 0 | AV11: 0 | AW11: 0 | AX11: 0 | AY11: 1 | AZ11: 1000 | BA11: 0 | BB11: =IF(B11="all",0,N11+ROUND(VLOOKUP(B11,'Fighter Stats'!$A$6:$E$8,5,FALSE)*O11/'Global Config'!$D$12,0)) -> 0 | BC11: =ROUND(BB11*(1-('Global Config'!$D$36/('Global Config'!$D$36+'Global Config'!$D$23))),0) -> 0 | BD11: Hypothesis | BE11: =IF(AND(A11<>"",H11<=I11,J11<=K11,S11<=R11,R11<=T11,Y11<=X11,X11<=Z11,AT11<=AS11,AS11<=AU11,AW11<=AX11,AY11>=1,L11>=0,M11>=0),"OK","ERROR") -> OK | BF11: Grab проходит через защиту; GuardBreak останавливает движение. | BG11: 0 | BH11: 3 | BI11: Startup|Active | BJ11: Startup|Active
A12: bear_body_check | B12: bear | C12: Таран корпусом | D12: Basic | E12: ApproachStrike | F12: strike|approach|knockback|medium | G12: 700 | H12: 900 | I12: 2100 | J12: 250 | K12: 950 | L12: 130 | M12: 0 | N12: 45 | O12: 650 | P12: 18 | Q12: 6 | R12: 5 | S12: 3 | T12: 8 | U12: 1 | V12: 0 | W12: 1 | X12: 10 | Y12: 7 | Z12: 15 | AA12: 25 | AB12: 35 | AC12: 35 | AD12: 0 | AE12: 35 | AF12: Armored | AG12: TRUE | AH12: TRUE | AI12: FALSE | AJ12: FALSE | AK12: FALSE | AL12: 0 | AM12: 0 | AN12: 0 | AO12: Approach | AP12: 1100 | AQ12: 80 | AR12: 3 | AS12: 850 | AT12: 300 | AU12: 1200 | AV12: 0 | AW12: 0 | AX12: 0 | AY12: 1 | AZ12: 1200 | BA12: 0 | BB12: =IF(B12="all",0,N12+ROUND(VLOOKUP(B12,'Fighter Stats'!$A$6:$E$8,5,FALSE)*O12/'Global Config'!$D$12,0)) -> 130 | BC12: =ROUND(BB12*(1-('Global Config'!$D$36/('Global Config'!$D$36+'Global Config'!$D$23))),0) -> 87 | BD12: Hypothesis | BE12: =IF(AND(A12<>"",H12<=I12,J12<=K12,S12<=R12,R12<=T12,Y12<=X12,X12<=Z12,AT12<=AS12,AS12<=AU12,AW12<=AX12,AY12>=1,L12>=0,M12>=0),"OK","ERROR") -> OK | BF12: Промах оставляет заметный recovery. | BG12: 2 | BH12: 3 | BI12: Startup | BJ12: Startup|Active
A13: bear_rampage_charge | B13: bear | C13: Неудержимый натиск | D13: Special | E13: SignatureApproach | F13: special|signature|approach|strike|unstoppable|wall_impact | G13: 500 | H13: 1600 | I13: 3600 | J13: 200 | K13: 1050 | L13: 300 | M13: 350 | N13: 90 | O13: 1200 | P13: 35 | Q13: 10 | R13: 12 | S13: 8 | T13: 18 | U13: 2 | V13: 0 | W13: 1 | X13: 18 | Y13: 12 | Z13: 26 | AA13: 80 | AB13: 65 | AC13: 70 | AD13: 0 | AE13: 65 | AF13: Unstoppable | AG13: TRUE | AH13: TRUE | AI13: FALSE | AJ13: TRUE | AK13: FALSE | AL13: 0 | AM13: 0 | AN13: 0 | AO13: Approach | AP13: 2600 | AQ13: 180 | AR13: 7 | AS13: 1400 | AT13: 600 | AU13: 1800 | AV13: 150 | AW13: 20 | AX13: 160 | AY13: 1 | AZ13: 2500 | BA13: 4 | BB13: =IF(B13="all",0,N13+ROUND(VLOOKUP(B13,'Fighter Stats'!$A$6:$E$8,5,FALSE)*O13/'Global Config'!$D$12,0)) -> 246 | BC13: =ROUND(BB13*(1-('Global Config'!$D$36/('Global Config'!$D$36+'Global Config'!$D$23))),0) -> 164 | BD13: Hypothesis | BE13: =IF(AND(A13<>"",H13<=I13,J13<=K13,S13<=R13,R13<=T13,Y13<=X13,X13<=Z13,AT13<=AS13,AS13<=AU13,AW13<=AX13,AY13>=1,L13>=0,M13>=0),"OK","ERROR") -> OK | BF13: Late Dodge остаётся контрplay; получает урон во время Unstoppable. | BG13: 3 | BH13: 1 | BI13: Startup | BJ13: Startup|Active | BK13: Stun|Knockdown
A14: bear_earthbreaker | B14: bear | C14: Землелом | D14: Special | E14: SignatureGround | F14: special|signature|heavy|ground|undodgeable|stagger | G14: 470 | H14: 300 | I14: 1700 | J14: 0 | K14: 2200 | L14: 250 | M14: 450 | N14: 80 | O14: 1000 | P14: 30 | Q14: 10 | R14: 14 | S14: 10 | T14: 20 | U14: 2 | V14: 0 | W14: 1 | X14: 17 | Y14: 12 | Z14: 25 | AA14: 75 | AB14: 60 | AC14: 60 | AD14: 0 | AE14: 60 | AF14: Committed | AG14: TRUE | AH14: FALSE | AI14: TRUE | AJ14: FALSE | AK14: FALSE | AL14: 0 | AM14: 0 | AN14: 0 | AO14: None | AP14: 0 | AQ14: 220 | AR14: 10 | AS14: 250 | AT14: 0 | AU14: 500 | AV14: 0 | AW14: 0 | AX14: 0 | AY14: 1 | AZ14: 2500 | BA14: 4 | BB14: =IF(B14="all",0,N14+ROUND(VLOOKUP(B14,'Fighter Stats'!$A$6:$E$8,5,FALSE)*O14/'Global Config'!$D$12,0)) -> 210 | BC14: =ROUND(BB14*(1-('Global Config'!$D$36/('Global Config'!$D$36+'Global Config'!$D$23))),0) -> 140 | BD14: Hypothesis | BE14: =IF(AND(A14<>"",H14<=I14,J14<=K14,S14<=R14,R14<=T14,Y14<=X14,X14<=Z14,AT14<=AS14,AS14<=AU14,AW14<=AX14,AY14>=1,L14>=0,M14>=0),"OK","ERROR") -> OK | BF14: Из geometry можно выйти до impact; DodgeChance не проверяется. | BG14: 3 | BH14: 1 | BI14: Startup
A15: bear_fury_maul | B15: bear | C15: Яростная расправа | D15: Special | E15: SignatureMultiHit | F15: special|signature|multi_hit|finisher|punish | G15: 420 | H15: 0 | I15: 850 | J15: 0 | K15: 1050 | L15: 350 | M15: 650 | N15: 28 | O15: 420 | P15: 10 | Q15: 3 | R15: 6 | S15: 4 | T15: 9 | U15: 12 | V15: 0|3|6|10 | W15: 4 | X15: 22 | Y15: 15 | Z15: 32 | AA15: 100 | AB15: 58 | AC15: 55 | AD15: 0 | AE15: 58 | AF15: UninterruptibleImpact | AG15: TRUE | AH15: TRUE | AI15: FALSE | AJ15: FALSE | AK15: FALSE | AL15: 0 | AM15: 0 | AN15: 0 | AO15: Follow | AP15: 350 | AQ15: 45 | AR15: 3 | AS15: 180 | AT15: 0 | AU15: 300 | AV15: 0 | AW15: 0 | AX15: 0 | AY15: 1 | AZ15: 2500 | BA15: 4 | BB15: =IF(B15="all",0,N15+ROUND(VLOOKUP(B15,'Fighter Stats'!$A$6:$E$8,5,FALSE)*O15/'Global Config'!$D$12,0)) -> 83 | BC15: =ROUND(BB15*(1-('Global Config'!$D$36/('Global Config'!$D$36+'Global Config'!$D$23))),0) -> 55 | BD15: Hypothesis | BE15: =IF(AND(A15<>"",H15<=I15,J15<=K15,S15<=R15,R15<=T15,Y15<=X15,X15<=Z15,AT15<=AS15,AS15<=AU15,AW15<=AX15,AY15>=1,L15>=0,M15>=0),"OK","ERROR") -> OK | BF15: Последний hit использует Punish multiplier 1.8x при Exposed/Stunned. | BG15: 2 | BH15: 1 | BI15: Startup
A16: kangaroo_lead_jab | B16: kangaroo | C16: Передний джеб | D16: Basic | E16: LightStrike | F16: strike|light|rhythm|fallback | G16: 1000 | H16: 100 | I16: 850 | J16: 0 | K16: 950 | L16: 0 | M16: 0 | N16: 22 | O16: 350 | P16: 9 | Q16: 3 | R16: 2 | S16: 1 | T16: 4 | U16: 1 | V16: 0 | W16: 1 | X16: 4 | Y16: 2 | Z16: 7 | AA16: 0 | AB16: 25 | AC16: 22 | AD16: 0 | AE16: 25 | AF16: Committed | AG16: TRUE | AH16: TRUE | AI16: FALSE | AJ16: FALSE | AK16: FALSE | AL16: 0 | AM16: 0 | AN16: 0 | AO16: None | AP16: 0 | AQ16: 15 | AR16: 0 | AS16: 0 | AT16: 0 | AU16: 0 | AV16: 0 | AW16: 0 | AX16: 0 | AY16: 2 | AZ16: 1000 | BA16: 0 | BB16: =IF(B16="all",0,N16+ROUND(VLOOKUP(B16,'Fighter Stats'!$A$6:$E$8,5,FALSE)*O16/'Global Config'!$D$12,0)) -> 57 | BC16: =ROUND(BB16*(1-('Global Config'!$D$36/('Global Config'!$D$36+'Global Config'!$D$23))),0) -> 38 | BD16: Hypothesis | BE16: =IF(AND(A16<>"",H16<=I16,J16<=K16,S16<=R16,R16<=T16,Y16<=X16,X16<=Z16,AT16<=AS16,AS16<=AU16,AW16<=AX16,AY16>=1,L16>=0,M16>=0),"OK","ERROR") -> OK | BF16: Даёт Rhythm только после другой категории. | BG16: 1 | BH16: 1 | BI16: Startup
A17: kangaroo_push_kick | B17: kangaroo | C17: Отталкивающий удар ногой | D17: Basic | E17: PokeStrike | F17: strike|poke|knockback|rhythm | G17: 780 | H17: 900 | I17: 1900 | J17: 400 | K17: 2000 | L17: 120 | M17: 0 | N17: 35 | O17: 550 | P17: 14 | Q17: 5 | R17: 5 | S17: 3 | T17: 8 | U17: 1 | V17: 0 | W17: 1 | X17: 8 | Y17: 5 | Z17: 12 | AA17: 20 | AB17: 32 | AC17: 30 | AD17: 0 | AE17: 32 | AF17: Committed | AG17: TRUE | AH17: TRUE | AI17: FALSE | AJ17: FALSE | AK17: FALSE | AL17: 0 | AM17: 0 | AN17: 0 | AO17: Push | AP17: 0 | AQ17: 55 | AR17: 2 | AS17: 700 | AT17: 250 | AU17: 1000 | AV17: 0 | AW17: 0 | AX17: 0 | AY17: 2 | AZ17: 1200 | BA17: 0 | BB17: =IF(B17="all",0,N17+ROUND(VLOOKUP(B17,'Fighter Stats'!$A$6:$E$8,5,FALSE)*O17/'Global Config'!$D$12,0)) -> 90 | BC17: =ROUND(BB17*(1-('Global Config'!$D$36/('Global Config'!$D$36+'Global Config'!$D$23))),0) -> 60 | BD17: Hypothesis | BE17: =IF(AND(A17<>"",H17<=I17,J17<=K17,S17<=R17,R17<=T17,Y17<=X17,X17<=Z17,AT17<=AS17,AS17<=AU17,AW17<=AX17,AY17>=1,L17>=0,M17>=0),"OK","ERROR") -> OK | BF17: Сохраняет mid range; blocked profile увеличивает recovery на 3 ticks. | BG17: 2 | BH17: 1 | BI17: Startup
A18: kangaroo_bounding_step | B18: kangaroo | C18: Пружинящий шаг | D18: Basic | E18: TempoMovement | F18: movement|adaptive|tempo|rhythm | G18: 850 | H18: 1000 | I18: 2200 | J18: 0 | K18: 0 | L18: 0 | M18: 0 | N18: 0 | O18: 0 | P18: 0 | Q18: 0 | R18: 1 | S18: 1 | T18: 2 | U18: 5 | W18: 0 | X18: 2 | Y18: 1 | Z18: 4 | AA18: 5 | AB18: 12 | AC18: 0 | AD18: 0 | AE18: 12 | AF18: Cancelable | AG18: FALSE | AH18: FALSE | AI18: FALSE | AJ18: FALSE | AK18: TRUE | AL18: 0 | AM18: 0 | AN18: 0 | AO18: Adaptive | AP18: 850 | AQ18: 0 | AR18: 0 | AS18: 0 | AT18: 0 | AU18: 0 | AV18: 0 | AW18: 0 | AX18: 0 | AY18: 3 | AZ18: 1000 | BA18: 0 | BB18: =IF(B18="all",0,N18+ROUND(VLOOKUP(B18,'Fighter Stats'!$A$6:$E$8,5,FALSE)*O18/'Global Config'!$D$12,0)) -> 0 | BC18: =ROUND(BB18*(1-('Global Config'!$D$36/('Global Config'!$D$36+'Global Config'!$D$23))),0) -> 0 | BD18: Hypothesis | BE18: =IF(AND(A18<>"",H18<=I18,J18<=K18,S18<=R18,R18<=T18,Y18<=X18,X18<=Z18,AT18<=AS18,AS18<=AU18,AW18<=AX18,AY18>=1,L18>=0,M18>=0),"OK","ERROR") -> OK | BF18: Tempo только за фактическое добровольное движение. | BG18: 0 | BH18: 1 | BI18: Startup|Active
A19: kangaroo_slip_hop | B19: kangaroo | C19: Скользящий отскок | D19: Basic | E19: DodgeMovement | F19: dodge|retreat|tempo|evade_grab | G19: 650 | H19: 1200 | I19: 2500 | J19: 0 | K19: 0 | L19: 100 | M19: 0 | N19: 0 | O19: 0 | P19: 0 | Q19: 0 | R19: 2 | S19: 1 | T19: 3 | U19: 4 | W19: 0 | X19: 6 | Y19: 4 | Z19: 9 | AA19: 15 | AB19: 50 | AC19: 0 | AD19: 0 | AE19: 80 | AF19: Committed | AG19: FALSE | AH19: FALSE | AI19: FALSE | AJ19: FALSE | AK19: FALSE | AL19: 0 | AM19: 0 | AN19: 650 | AO19: Retreat | AP19: 700 | AQ19: 0 | AR19: 0 | AS19: 0 | AT19: 0 | AU19: 0 | AV19: 0 | AW19: 0 | AX19: 0 | AY19: 1 | AZ19: 1200 | BA19: 0 | BB19: =IF(B19="all",0,N19+ROUND(VLOOKUP(B19,'Fighter Stats'!$A$6:$E$8,5,FALSE)*O19/'Global Config'!$D$12,0)) -> 0 | BC19: =ROUND(BB19*(1-('Global Config'!$D$36/('Global Config'!$D$36+'Global Config'!$D$23))),0) -> 0 | BD19: Hypothesis | BE19: =IF(AND(A19<>"",H19<=I19,J19<=K19,S19<=R19,R19<=T19,Y19<=X19,X19<=Z19,AT19<=AS19,AS19<=AU19,AW19<=AX19,AY19>=1,L19>=0,M19>=0),"OK","ERROR") -> OK | BF19: EvadeGrab требует выхода из grab range; у стены сильно штрафуется. | BG19: 0 | BH19: 1 | BI19: Startup
A20: kangaroo_flying_kick | B20: kangaroo | C20: Летящий удар | D20: Special | E20: SignatureApproach | F20: special|signature|approach|strike|knockback|wall_impact | G20: 520 | H20: 1500 | I20: 3300 | J20: 200 | K20: 1150 | L20: 260 | M20: 350 | N20: 65 | O20: 850 | P20: 24 | Q20: 7 | R20: 7 | S20: 4 | T20: 11 | U20: 1 | V20: 0 | W20: 1 | X20: 14 | Y20: 9 | Z20: 21 | AA20: 60 | AB20: 62 | AC20: 62 | AD20: 0 | AE20: 62 | AF20: Committed | AG20: TRUE | AH20: TRUE | AI20: FALSE | AJ20: TRUE | AK20: FALSE | AL20: 0 | AM20: 0 | AN20: 0 | AO20: Approach | AP20: 2300 | AQ20: 125 | AR20: 5 | AS20: 1100 | AT20: 450 | AU20: 1500 | AV20: 90 | AW20: 10 | AX20: 90 | AY20: 1 | AZ20: 2500 | BA20: 4 | BB20: =IF(B20="all",0,N20+ROUND(VLOOKUP(B20,'Fighter Stats'!$A$6:$E$8,5,FALSE)*O20/'Global Config'!$D$12,0)) -> 150 | BC20: =ROUND(BB20*(1-('Global Config'!$D$36/('Global Config'!$D$36+'Global Config'!$D$23))),0) -> 100 | BD20: Hypothesis | BE20: =IF(AND(A20<>"",H20<=I20,J20<=K20,S20<=R20,R20<=T20,Y20<=X20,X20<=Z20,AT20<=AS20,AS20<=AU20,AW20<=AX20,AY20>=1,L20>=0,M20>=0),"OK","ERROR") -> OK | BF20: Сильный punish, но Block/miss дают длинный recovery. | BG20: 2 | BH20: 1 | BI20: Startup
A21: kangaroo_tail_counter | B21: kangaroo | C21: Контрудар хвостом | D21: Special | E21: SignatureCounter | F21: special|signature|counter|position|rhythm | G21: 460 | H21: 200 | I21: 1500 | J21: 0 | K21: 1600 | L21: 200 | M21: 400 | N21: 55 | O21: 700 | P21: 20 | Q21: 6 | R21: 2 | S21: 1 | T21: 4 | U21: 6 | V21: counter:0 | W21: 1 | X21: 16 | Y21: 10 | Z21: 24 | AA21: 70 | AB21: 75 | AC21: 75 | AD21: 0 | AE21: 90 | AF21: UninterruptibleImpact | AG21: TRUE | AH21: FALSE | AI21: FALSE | AJ21: FALSE | AK21: TRUE | AL21: 0 | AM21: 0 | AN21: 0 | AO21: Swap | AP21: 500 | AQ21: 100 | AR21: 4 | AS21: 450 | AT21: 100 | AU21: 700 | AV21: 0 | AW21: 0 | AX21: 0 | AY21: 1 | AZ21: 2200 | BA21: 0 | BB21: =IF(B21="all",0,N21+ROUND(VLOOKUP(B21,'Fighter Stats'!$A$6:$E$8,5,FALSE)*O21/'Global Config'!$D$12,0)) -> 125 | BC21: =ROUND(BB21*(1-('Global Config'!$D$36/('Global Config'!$D$36+'Global Config'!$D$23))),0) -> 83 | BD21: Hypothesis | BE21: =IF(AND(A21<>"",H21<=I21,J21<=K21,S21<=R21,R21<=T21,Y21<=X21,X21<=Z21,AT21<=AS21,AS21<=AU21,AW21<=AX21,AY21>=1,L21>=0,M21>=0),"OK","ERROR") -> OK | BF21: Legal только после наблюдаемого разрешённого telegraph. | BG21: 2 | BH21: 1 | BI21: Startup
A22: kangaroo_tempo_barrage | B22: kangaroo | C22: Серия в темпе | D22: Special | E22: SignatureMultiHit | F22: special|signature|multi_hit|finisher|rhythm | G22: 420 | H22: 200 | I22: 1600 | J22: 0 | K22: 1600 | L22: 300 | M22: 650 | N22: 18 | O22: 260 | P22: 7 | Q22: 2 | R22: 4 | S22: 2 | T22: 7 | U22: 14 | V22: 0|3|6|9|13 | W22: 5 | X22: 20 | Y22: 13 | Z22: 30 | AA22: 90 | AB22: 57 | AC22: 50 | AD22: 0 | AE22: 57 | AF22: UninterruptibleImpact | AG22: TRUE | AH22: TRUE | AI22: FALSE | AJ22: FALSE | AK22: TRUE | AL22: 0 | AM22: 0 | AN22: 0 | AO22: Follow | AP22: 500 | AQ22: 35 | AR22: 2 | AS22: 120 | AT22: 0 | AU22: 220 | AV22: 0 | AW22: 0 | AX22: 0 | AY22: 1 | AZ22: 2500 | BA22: 4 | BB22: =IF(B22="all",0,N22+ROUND(VLOOKUP(B22,'Fighter Stats'!$A$6:$E$8,5,FALSE)*O22/'Global Config'!$D$12,0)) -> 44 | BC22: =ROUND(BB22*(1-('Global Config'!$D$36/('Global Config'!$D$36+'Global Config'!$D$23))),0) -> 29 | BD22: Hypothesis | BE22: =IF(AND(A22<>"",H22<=I22,J22<=K22,S22<=R22,R22<=T22,Y22<=X22,X22<=Z22,AT22<=AS22,AS22<=AU22,AW22<=AX22,AY22>=1,L22>=0,M22>=0),"OK","ERROR") -> OK | BF22: Один Dodge не отменяет последующие hit groups; финальный hit 1.5x при Exposed. | BG22: 1 | BH22: 1 | BI22: Startup
A23: gorilla_hammer_fist | B23: gorilla | C23: Молотящий кулак | D23: Basic | E23: MediumStrike | F23: strike|medium|pressure|fallback | G23: 1000 | H23: 100 | I23: 950 | J23: 0 | K23: 1050 | L23: 0 | M23: 0 | N23: 35 | O23: 500 | P23: 13 | Q23: 4 | R23: 4 | S23: 2 | T23: 6 | U23: 1 | V23: 0 | W23: 1 | X23: 6 | Y23: 4 | Z23: 9 | AA23: 0 | AB23: 28 | AC23: 30 | AD23: 0 | AE23: 28 | AF23: Committed | AG23: TRUE | AH23: TRUE | AI23: FALSE | AJ23: FALSE | AK23: FALSE | AL23: 0 | AM23: 0 | AN23: 0 | AO23: None | AP23: 0 | AQ23: 35 | AR23: 0 | AS23: 0 | AT23: 0 | AU23: 0 | AV23: 0 | AW23: 0 | AX23: 0 | AY23: 2 | AZ23: 1000 | BA23: 0 | BB23: =IF(B23="all",0,N23+ROUND(VLOOKUP(B23,'Fighter Stats'!$A$6:$E$8,5,FALSE)*O23/'Global Config'!$D$12,0)) -> 90 | BC23: =ROUND(BB23*(1-('Global Config'!$D$36/('Global Config'!$D$36+'Global Config'!$D$23))),0) -> 60 | BD23: Hypothesis | BE23: =IF(AND(A23<>"",H23<=I23,J23<=K23,S23<=R23,R23<=T23,Y23<=X23,X23<=Z23,AT23<=AS23,AS23<=AU23,AW23<=AX23,AY23>=1,L23>=0,M23>=0),"OK","ERROR") -> OK | BF23: Стабильный pressure action. | BG23: 2 | BH23: 1 | BI23: Startup
A24: gorilla_driving_shove | B24: gorilla | C24: Давящий толчок | D24: Basic | E24: ShoveStrike | F24: strike|knockback|grip_generator|position | G24: 820 | H24: 100 | I24: 800 | J24: 0 | K24: 900 | L24: 110 | M24: 0 | N24: 20 | O24: 250 | P24: 8 | Q24: 3 | R24: 4 | S24: 2 | T24: 6 | U24: 1 | V24: 0 | W24: 1 | X24: 8 | Y24: 5 | Z24: 12 | AA24: 18 | AB24: 36 | AC24: 35 | AD24: 0 | AE24: 36 | AF24: Committed | AG24: TRUE | AH24: TRUE | AI24: FALSE | AJ24: FALSE | AK24: FALSE | AL24: 0 | AM24: 0 | AN24: 0 | AO24: Push | AP24: 0 | AQ24: 60 | AR24: 2 | AS24: 900 | AT24: 350 | AU24: 1250 | AV24: 0 | AW24: 0 | AX24: 0 | AY24: 2 | AZ24: 1200 | BA24: 0 | BB24: =IF(B24="all",0,N24+ROUND(VLOOKUP(B24,'Fighter Stats'!$A$6:$E$8,5,FALSE)*O24/'Global Config'!$D$12,0)) -> 48 | BC24: =ROUND(BB24*(1-('Global Config'!$D$36/('Global Config'!$D$36+'Global Config'!$D$23))),0) -> 32 | BD24: Hypothesis | BE24: =IF(AND(A24<>"",H24<=I24,J24<=K24,S24<=R24,R24<=T24,Y24<=X24,X24<=Z24,AT24<=AS24,AS24<=AU24,AW24<=AX24,AY24>=1,L24>=0,M24>=0),"OK","ERROR") -> OK | BF24: Grip начисляется только на resolved hit. | BG24: 2 | BH24: 1 | BI24: Startup
A25: gorilla_high_guard | B25: gorilla | C25: Высокая защита | D25: Basic | E25: Block | F25: block|defense|grip_generator | G25: 700 | H25: 0 | I25: 1800 | J25: 0 | K25: 0 | L25: 90 | M25: 0 | N25: 0 | O25: 0 | P25: 0 | Q25: 0 | R25: 2 | S25: 1 | T25: 4 | U25: 12 | W25: 0 | X25: 6 | Y25: 4 | Z25: 9 | AA25: 15 | AB25: 40 | AC25: 0 | AD25: 0 | AE25: 85 | AF25: Committed | AG25: FALSE | AH25: FALSE | AI25: FALSE | AJ25: FALSE | AK25: FALSE | AL25: 700 | AM25: 650 | AN25: 0 | AO25: None | AP25: 0 | AQ25: 0 | AR25: 0 | AS25: 0 | AT25: 0 | AU25: 0 | AV25: 0 | AW25: 0 | AX25: 0 | AY25: 1 | AZ25: 1200 | BA25: 0 | BB25: =IF(B25="all",0,N25+ROUND(VLOOKUP(B25,'Fighter Stats'!$A$6:$E$8,5,FALSE)*O25/'Global Config'!$D$12,0)) -> 0 | BC25: =ROUND(BB25*(1-('Global Config'!$D$36/('Global Config'!$D$36+'Global Config'!$D$23))),0) -> 0 | BD25: Hypothesis | BE25: =IF(AND(A25<>"",H25<=I25,J25<=K25,S25<=R25,R25<=T25,Y25<=X25,X25<=Z25,AT25<=AS25,AS25<=AU25,AW25<=AX25,AY25>=1,L25>=0,M25>=0),"OK","ERROR") -> OK | BF25: Grab и GuardBreak остаются основным контрplay. | BG25: 0 | BH25: 1 | BI25: Startup
A26: gorilla_clinch_check | B26: gorilla | C26: Проверка клинча | D26: Basic | E26: Grab | F26: grab|position|grip_generator|pull | G26: 620 | H26: 0 | I26: 650 | J26: 0 | K26: 700 | L26: 120 | M26: 0 | N26: 0 | O26: 0 | P26: 0 | Q26: 0 | R26: 5 | S26: 3 | T26: 8 | U26: 1 | V26: grab:0 | W26: 0 | X26: 10 | Y26: 7 | Z26: 15 | AA26: 30 | AB26: 45 | AC26: 0 | AD26: 55 | AE26: 55 | AF26: Committed | AG26: FALSE | AH26: FALSE | AI26: FALSE | AJ26: FALSE | AK26: TRUE | AL26: 0 | AM26: 0 | AN26: 0 | AO26: Pull | AP26: 400 | AQ26: 35 | AR26: 0 | AS26: 400 | AT26: 150 | AU26: 600 | AV26: 0 | AW26: 0 | AX26: 0 | AY26: 1 | AZ26: 1200 | BA26: 0 | BB26: =IF(B26="all",0,N26+ROUND(VLOOKUP(B26,'Fighter Stats'!$A$6:$E$8,5,FALSE)*O26/'Global Config'!$D$12,0)) -> 0 | BC26: =ROUND(BB26*(1-('Global Config'!$D$36/('Global Config'!$D$36+'Global Config'!$D$23))),0) -> 0 | BD26: Hypothesis | BE26: =IF(AND(A26<>"",H26<=I26,J26<=K26,S26<=R26,R26<=T26,Y26<=X26,X26<=Z26,AT26<=AS26,AS26<=AU26,AW26<=AX26,AY26>=1,L26>=0,M26>=0),"OK","ERROR") -> OK | BF26: Немедленный pull/release без длительного удержания. | BG26: 0 | BH26: 1 | BI26: Startup
A27: gorilla_pivot_throw | B27: gorilla | C27: Разворотный бросок | D27: Special | E27: SignatureGrab | F27: special|signature|grab|throw|swap|knockdown | G27: 500 | H27: 0 | I27: 650 | J27: 0 | K27: 700 | L27: 230 | M27: 400 | N27: 60 | O27: 700 | P27: 22 | Q27: 0 | R27: 7 | S27: 4 | T27: 11 | U27: 6 | V27: grab:0|throw:5 | W27: 1 | X27: 15 | Y27: 10 | Z27: 23 | AA27: 70 | AB27: 70 | AC27: 0 | AD27: 75 | AE27: 75 | AF27: Committed | AG27: FALSE | AH27: FALSE | AI27: FALSE | AJ27: FALSE | AK27: TRUE | AL27: 0 | AM27: 0 | AN27: 0 | AO27: Swap | AP27: 900 | AQ27: 170 | AR27: 8 | AS27: 900 | AT27: 400 | AU27: 1300 | AV27: 0 | AW27: 0 | AX27: 0 | AY27: 1 | AZ27: 2500 | BA27: 4 | BB27: =IF(B27="all",0,N27+ROUND(VLOOKUP(B27,'Fighter Stats'!$A$6:$E$8,5,FALSE)*O27/'Global Config'!$D$12,0)) -> 137 | BC27: =ROUND(BB27*(1-('Global Config'!$D$36/('Global Config'!$D$36+'Global Config'!$D$23))),0) -> 91 | BD27: Hypothesis | BE27: =IF(AND(A27<>"",H27<=I27,J27<=K27,S27<=R27,R27<=T27,Y27<=X27,X27<=Z27,AT27<=AS27,AS27<=AU27,AW27<=AX27,AY27>=1,L27>=0,M27>=0),"OK","ERROR") -> OK | BF27: MaxHoldTicks=6; reversal у собственной стены. | BG27: 0 | BH27: 1 | BI27: Startup
A28: gorilla_overhead_pound | B28: gorilla | C28: Удар сверху | D28: Special | E28: HeavyGround | F28: special|heavy|ground_hit|stagger|punish | G28: 440 | H28: 100 | I28: 950 | J28: 0 | K28: 1050 | L28: 260 | M28: 350 | N28: 85 | O28: 1050 | P28: 30 | Q28: 9 | R28: 12 | S28: 8 | T28: 18 | U28: 1 | V28: 0 | W28: 1 | X28: 16 | Y28: 11 | Z28: 24 | AA28: 70 | AB28: 63 | AC28: 65 | AD28: 0 | AE28: 63 | AF28: Committed | AG28: TRUE | AH28: TRUE | AI28: FALSE | AJ28: FALSE | AK28: FALSE | AL28: 0 | AM28: 0 | AN28: 0 | AO28: None | AP28: 0 | AQ28: 240 | AR28: 10 | AS28: 250 | AT28: 0 | AU28: 450 | AV28: 0 | AW28: 0 | AX28: 0 | AY28: 1 | AZ28: 2200 | BA28: 3 | BB28: =IF(B28="all",0,N28+ROUND(VLOOKUP(B28,'Fighter Stats'!$A$6:$E$8,5,FALSE)*O28/'Global Config'!$D$12,0)) -> 201 | BC28: =ROUND(BB28*(1-('Global Config'!$D$36/('Global Config'!$D$36+'Global Config'!$D$23))),0) -> 134 | BD28: Hypothesis | BE28: =IF(AND(A28<>"",H28<=I28,J28<=K28,S28<=R28,R28<=T28,Y28<=X28,X28<=Z28,AT28<=AS28,AS28<=AU28,AW28<=AX28,AY28>=1,L28>=0,M28>=0),"OK","ERROR") -> OK | BF28: Высокий вес только против Stunned/KnockedDown/Exposed. | BG28: 3 | BH28: 1 | BI28: Startup
A29: gorilla_wall_breaker | B29: gorilla | C29: Сокрушение о стену | D29: Special | E29: SignatureWallGrab | F29: special|signature|grab|wall_impact|finisher|knockdown | G29: 400 | H29: 0 | I29: 650 | J29: 0 | K29: 700 | L29: 320 | M29: 650 | N29: 75 | O29: 800 | P29: 28 | Q29: 0 | R29: 8 | S29: 5 | T29: 12 | U29: 4 | V29: grab:0|wall:3 | W29: 1 | X29: 20 | Y29: 14 | Z29: 30 | AA29: 100 | AB29: 78 | AC29: 0 | AD29: 82 | AE29: 82 | AF29: Committed | AG29: FALSE | AH29: FALSE | AI29: FALSE | AJ29: TRUE | AK29: TRUE | AL29: 0 | AM29: 0 | AN29: 0 | AO29: Push | AP29: 1000 | AQ29: 230 | AR29: 10 | AS29: 1000 | AT29: 300 | AU29: 1400 | AV29: 250 | AW29: 40 | AX29: 180 | AY29: 1 | AZ29: 2500 | BA29: 4 | BB29: =IF(B29="all",0,N29+ROUND(VLOOKUP(B29,'Fighter Stats'!$A$6:$E$8,5,FALSE)*O29/'Global Config'!$D$12,0)) -> 163 | BC29: =ROUND(BB29*(1-('Global Config'!$D$36/('Global Config'!$D$36+'Global Config'!$D$23))),0) -> 109 | BD29: Hypothesis | BE29: =IF(AND(A29<>"",H29<=I29,J29<=K29,S29<=R29,R29<=T29,Y29<=X29,X29<=Z29,AT29<=AS29,AS29<=AU29,AW29<=AX29,AY29>=1,L29>=0,M29>=0),"OK","ERROR") -> OK | BF29: Legal только в wall zone и при отсутствии GrabLockout. | BG29: 0 | BH29: 1 | BI29: Startup

Sheet Passives
A1: Passive Skills
A2: Шесть пассивов стартовых животных
A3: Все trigger chains имеют InternalCooldown или MaxActivations. Пассив не может отменять MinDamage, GrabLockout, ControlImmunity или MaxHoldTicks.
A5: Passive ID | B5: Animal ID | C5: Display Name RU | D5: Trigger | E5: Conditions | F5: Effect ID | G5: Modifier Stat 1 | H5: Operation 1 | I5: Value 1 | J5: Modifier Stat 2 | K5: Operation 2 | L5: Value 2 | M5: Duration Ticks | N5: Internal Cooldown Ticks | O5: Stack Cap | P5: Max Activations / Tick | Q5: Max Activations / Battle | R5: Resource Gain | S5: Weight Multiplier FP | T5: Tags | U5: Status | V5: Validation | W5: Notes RU
A6: bear_thick_hide | B6: bear | C6: Толстая шкура | D6: OnDamageTaken | E6: valid_strike; internal_cooldown_ready | F6: effect_bear_thick_hide | G6: Armor | H6: Multiply | I6: 1150 | J6: ControlResistance | K6: Multiply | L6: 1150 | M6: 25 | N6: 50 | O6: 1 | P6: 1 | Q6: 99 | R6: 0 | S6: 1000 | T6: defense|comeback | U6: Hypothesis | V6: =IF(AND(A6<>"",B6<>"",P6>=1,Q6>=1,O6>=1,S6>=250,S6<=3000),"OK","ERROR") -> OK | W6: Refresh/StrongestWins; не опускает damage ниже MinDamage.
A7: bear_pressure_fuels_rage | B7: bear | C7: Давление питает ярость | D7: OnDamageTaken|OnBlockedHeavy|OnHeavyHit | E7: eligible_source_event; once_per_event | G7: RageGain | H7: Multiply | I7: 1250 | J7: SignatureWeight | K7: Multiply | L7: 1125 | M7: 0 | N7: 0 | O7: 1 | P7: 3 | Q7: 999 | R7: 0 | S7: 1125 | T7: resource|signature|comeback | U7: Hypothesis | V7: =IF(AND(A7<>"",B7<>"",P7>=1,Q7>=1,O7>=1,S7>=250,S7<=3000),"OK","ERROR") -> OK | W7: Chip eligibility задаётся trigger filter; cap per tick обязателен.
A8: kangaroo_never_still | B8: kangaroo | C8: Всегда в движении | D8: OnVoluntaryDistanceMoved|OnTempoDecayStart | E8: voluntary_movement_only | G8: TempoPerUnit | H8: Multiply | I8: 1250 | J8: DecayGraceTicks | K8: Add | L8: 10 | M8: 0 | N8: 0 | O8: 1 | P8: 1 | Q8: 999 | R8: 0 | S8: 1100 | T8: movement|resource | U8: Hypothesis | V8: =IF(AND(A8<>"",B8<>"",P8>=1,Q8>=1,O8>=1,S8>=250,S8<=3000),"OK","ERROR") -> OK | W8: Forced movement и separation correction не считаются.
A9: kangaroo_clean_rhythm | B9: kangaroo | C9: Чистый ритм | D9: OnNewCategoryHit | E9: category_changed; internal_cooldown_ready | F9: effect_kangaroo_clean_rhythm | G9: Precision | H9: Add | I9: 8 | J9: ActionSpeed | K9: Add | L9: 5 | M9: 20 | N9: 8 | O9: 3 | P9: 1 | Q9: 99 | R9: 60 | S9: 1100 | T9: rhythm|resource|speed | U9: Hypothesis | V9: =IF(AND(A9<>"",B9<>"",P9>=1,Q9>=1,O9>=1,S9>=250,S9<=3000),"OK","ERROR") -> OK | W9: Multi-hit считается одной category opportunity; hard control сбрасывает.
A10: gorilla_territorial_pressure | B10: gorilla | C10: Территориальное давление | D10: EndOfTick|OnDrivingShove | E10: opponent_in_wall_zone; engagement; not_hard_controlled | F10: effect_gorilla_wall_pressure | G10: WallActionWeight | H10: Multiply | I10: 1250 | J10: GripGain | K10: Add | L10: 10 | M10: 10 | N10: 5 | O10: 1 | P10: 1 | Q10: 999 | R10: 10 | S10: 1250 | T10: wall|resource|position | U10: Hypothesis | V10: =IF(AND(A10<>"",B10<>"",P10>=1,Q10>=1,O10>=1,S10>=250,S10<=3000),"OK","ERROR") -> OK | W10: Rate-limited; не начисляется вне engagement.
A11: gorilla_iron_grip | B11: gorilla | C11: Железная хватка | D11: OnGrabStarted|OnGrabResolved | E11: grab_legal; once_per_lifecycle | F11: effect_gorilla_iron_grip | G11: GrabPriority | H11: Add | I11: 8 | J11: ControlPower | K11: Add | L11: 12 | M11: 12 | N11: 15 | O11: 1 | P11: 1 | Q11: 99 | R11: 0 | S11: 1150 | T11: grab|control | U11: Hypothesis | V11: =IF(AND(A11<>"",B11<>"",P11>=1,Q11>=1,O11>=1,S11>=250,S11<=3000),"OK","ERROR") -> OK | W11: Не изменяет MaxHoldTicks, GrabLockout или immunity.

Sheet Effects
A1: Effects
A2: Общие временные эффекты, stacking policies и anti-loop окна
A3: State Stunned/KnockedDown/Grabbed остаётся в машине состояний; здесь находятся только эффекты, модификаторы, immunity и lockout.
A5: Effect ID | B5: Display Name RU | C5: Duration Ticks | D5: Expiry Boundary | E5: Stack Group | F5: Stack Policy | G5: Stack Cap | H5: Compare Key | I5: Modifier Stat 1 | J5: Operation 1 | K5: Value 1 | L5: Modifier Stat 2 | M5: Operation 2 | N5: Value 2 | O5: Tags | P5: Max Activations / Tick | Q5: Max Activations / Battle | R5: Internal Cooldown Ticks | S5: Lookup Profile | T5: Status | U5: Validation | V5: Notes RU | W5: Priority | X5: Refresh Rule | Y5: Semantic Role
A6: effect_bear_thick_hide | B6: Толстая шкура: усиление | C6: 25 | D6: ExpireAfterTick | E6: bear_thick_hide | F6: StrongestWins | G6: 1 | H6: Value1 | I6: Armor | J6: Multiply | K6: 1150 | L6: ControlResistance | M6: Multiply | N6: 1150 | O6: buff|defense | P6: 1 | Q6: 99 | R6: 50 | T6: Hypothesis | U6: =IF(AND(A6<>"",C6>=0,G6>=1,P6>=1,Q6>=1),"OK","ERROR") -> OK | V6: Источник — passive.bear_thick_hide. | W6: 0 | X6: ResetDuration | Y6: None
A7: effect_kangaroo_clean_rhythm | B7: Чистый ритм | C7: 20 | D7: ExpireAfterTick | E7: kangaroo_clean_rhythm | F7: AddStacks | G7: 3 | H7: StackCount | I7: Precision | J7: Add | K7: 8 | L7: ActionSpeed | M7: Add | N7: 5 | O7: buff|rhythm|speed | P7: 1 | Q7: 99 | R7: 8 | T7: Hypothesis | U7: =IF(AND(A7<>"",C7>=0,G7>=1,P7>=1,Q7>=1),"OK","ERROR") -> OK | V7: Сброс при repeat category или hard control. | W7: 0 | X7: ResetDuration | Y7: None
A8: effect_gorilla_wall_pressure | B8: Территориальное давление | C8: 10 | D8: ExpireAfterTick | E8: gorilla_wall_pressure | F8: Refresh | G8: 1 | H8: DurationTicks | I8: WallActionWeight | J8: Multiply | K8: 1250 | L8: GripGain | M8: Add | N8: 10 | O8: buff|wall|resource | P8: 1 | Q8: 999 | R8: 5 | T8: Hypothesis | U8: =IF(AND(A8<>"",C8>=0,G8>=1,P8>=1,Q8>=1),"OK","ERROR") -> OK | V8: Действует только пока соблюдены wall/engagement conditions. | W8: 0 | X8: ResetDuration | Y8: None
A9: effect_gorilla_iron_grip | B9: Железная хватка | C9: 12 | D9: ExpireAfterTick | E9: gorilla_iron_grip | F9: Refresh | G9: 1 | H9: DurationTicks | I9: GrabPriority | J9: Add | K9: 8 | L9: ControlPower | M9: Add | N9: 12 | O9: buff|grab|control | P9: 1 | Q9: 99 | R9: 15 | T9: Hypothesis | U9: =IF(AND(A9<>"",C9>=0,G9>=1,P9>=1,Q9>=1),"OK","ERROR") -> OK | V9: Не изменяет anti-loop limits. | W9: 0 | X9: ResetDuration | Y9: None
A10: effect_guard_broken | B10: Защита сломана | C10: 15 | D10: ExpireAfterTick | E10: guard_broken | F10: Refresh | G10: 1 | H10: DurationTicks | I10: Guard | J10: Add | K10: -30 | L10: BlockWeight | M10: Multiply | N10: 650 | O10: debuff|guard_break|exposed | P10: 1 | Q10: 99 | R10: 0 | T10: Hypothesis | U10: =IF(AND(A10<>"",C10>=0,G10>=1,P10>=1,Q10>=1),"OK","ERROR") -> OK | V10: Не отключает Block полностью. | W10: 0 | X10: ResetDuration | Y10: GuardBreak
A11: effect_exposed | B11: Открыт для наказания | C11: 12 | D11: ExpireAfterTick | E11: exposed | F11: Refresh | G11: 1 | H11: DurationTicks | I11: DamageTaken | J11: Multiply | K11: 1250 | L11: PunishWeight | M11: Multiply | N11: 1400 | O11: debuff|exposed|punish | P11: 1 | Q11: 99 | R11: 0 | T11: Hypothesis | U11: =IF(AND(A11<>"",C11>=0,G11>=1,P11>=1,Q11>=1),"OK","ERROR") -> OK | V11: Все усиления объясняются reason code Exposed. | W11: 0 | X11: ResetDuration | Y11: None
A12: effect_control_fatigue | B12: Усталость от контроля | C12: 100 | D12: ExpireAfterTick | E12: control_fatigue | F12: AddStacks | G12: 3 | H12: StackCount | I12: HardControlDuration | J12: Multiply | K12: 1000 | M12: Override | N12: 0 | O12: debuff|hard_control|anti_loop | P12: 1 | Q12: 999 | R12: 0 | S12: 1000|750|500|250 | T12: Hypothesis | U12: =IF(AND(A12<>"",C12>=0,G12>=1,P12>=1,Q12>=1),"OK","ERROR") -> OK | V12: При stack 3 создаёт ControlImmunity. | W12: 0 | X12: ResetDuration | Y12: ControlFatigue
A13: effect_control_immunity | B13: Иммунитет к контролю | C13: 25 | D13: ExpireAfterTick | E13: control_immunity | F13: Reject | G13: 1 | H13: DurationTicks | I13: HardControlAllowed | J13: Override | K13: 0 | M13: Override | N13: 0 | O13: buff|immunity|anti_loop | P13: 1 | Q13: 999 | R13: 0 | T13: Hypothesis | U13: =IF(AND(A13<>"",C13>=0,G13>=1,P13>=1,Q13>=1),"OK","ERROR") -> OK | V13: Новый hard control не refresh-ит immunity. | W13: 0 | X13: ResetDuration | Y13: ControlImmunity
A14: effect_grab_lockout | B14: Запрет повторного захвата | C14: 20 | D14: ExpireAfterTick | E14: grab_lockout | F14: Reject | G14: 1 | H14: DurationTicks | I14: GrabAllowed | J14: Override | K14: 0 | M14: Override | N14: 0 | O14: debuff|grab|anti_loop | P14: 1 | Q14: 999 | R14: 0 | T14: Hypothesis | U14: =IF(AND(A14<>"",C14>=0,G14>=1,P14>=1,Q14>=1),"OK","ERROR") -> OK | V14: Блокирует любой новый grab до окончания. | W14: 0 | X14: ResetDuration | Y14: GrabLockout
A15: effect_wakeup_immunity | B15: Защита после падения | C15: 25 | D15: ExpireAfterTick | E15: wakeup_immunity | F15: Reject | G15: 1 | H15: DurationTicks | I15: KnockdownAllowed | J15: Override | K15: 0 | M15: Override | N15: 0 | O15: buff|knockdown|anti_loop | P15: 1 | Q15: 999 | R15: 0 | T15: Hypothesis | U15: =IF(AND(A15<>"",C15>=0,G15>=1,P15>=1,Q15>=1),"OK","ERROR") -> OK | V15: GroundHit damage разрешён, новый KnockedDown — нет. | W15: 0 | X15: ResetDuration | Y15: WakeupImmunity

Sheet Tactics
A1: Tactics
A2: Четыре универсальные тактики как множители тегов и ситуаций
A3: Тактика меняет только веса выбора и perception delay; скрытых бонусов урона против AnimalId нет.
A5: Tactic ID | B5: Display Name RU | C5: Approach FP | D5: Retreat FP | E5: Light FP | F5: Heavy FP | G5: Block FP | H5: Dodge FP | I5: Counter FP | J5: Grab FP | K5: Signature FP | L5: Resource Generator FP | M5: Resource Spender FP | N5: Target Recovery FP | O5: Target Wall FP | P5: Self Wall FP | Q5: Low HP FP | R5: Perception Delay Ticks | S5: Repeat Penalty FP | T5: Notes RU | U5: Status | V5: Validation
A6: tactic_pressure | B6: Давление | C6: 1250 | D6: 750 | E6: 1150 | F6: 1100 | G6: 850 | H6: 850 | I6: 800 | J6: 1100 | K6: 1050 | L6: 1000 | M6: 1150 | N6: 1200 | O6: 1150 | P6: 900 | Q6: 1000 | R6: 5 | S6: 850 | T6: Сближается и раньше тратит энергию; уязвима к counter и стене. | U6: Hypothesis | V6: =IF(AND(A6<>"",C6>=250,C6<=3000,D6>=250,D6<=3000,K6>=250,K6<=3000,R6>=1,S6>=250,S6<=1000),"OK","ERROR") -> OK
A7: tactic_counter | B7: Ответная игра | C7: 850 | D7: 1100 | E7: 900 | F7: 900 | G7: 1350 | H7: 1300 | I7: 1450 | J7: 1050 | K7: 950 | L7: 1050 | M7: 850 | N7: 1400 | O7: 900 | P7: 1050 | Q7: 1150 | R7: 3 | S7: 750 | T7: Сохраняет ресурс и реагирует на telegraph; может отдать пространство. | U7: Hypothesis | V7: =IF(AND(A7<>"",C7>=250,C7<=3000,D7>=250,D7<=3000,K7>=250,K7<=3000,R7>=1,S7>=250,S7<=1000),"OK","ERROR") -> OK
A8: tactic_position | B8: Позиция | C8: 1000 | D8: 1250 | E8: 900 | F8: 950 | G8: 1000 | H8: 1150 | I8: 1050 | J8: 1100 | K8: 1050 | L8: 1150 | M8: 950 | N8: 1050 | O8: 1400 | P8: 1350 | Q8: 1000 | R8: 5 | S8: 800 | T8: Держит preferred range, использует knockback, escape и wall opportunities. | U8: Hypothesis | V8: =IF(AND(A8<>"",C8>=250,C8<=3000,D8>=250,D8<=3000,K8>=250,K8<=3000,R8>=1,S8>=250,S8<=1000),"OK","ERROR") -> OK
A9: tactic_signature | B9: Фирменный план | C9: 1050 | D9: 900 | E9: 850 | F9: 1000 | G9: 950 | H9: 950 | I9: 1000 | J9: 1050 | K9: 1450 | L9: 1350 | M9: 1250 | N9: 1150 | O9: 1200 | P9: 1000 | Q9: 1200 | R9: 5 | S9: 800 | T9: Копит уникальный ресурс и использует opportunity profile; план читаем. | U9: Hypothesis | V9: =IF(AND(A9<>"",C9>=250,C9<=3000,D9>=250,D9<=3000,K9>=250,K9<=3000,R9>=1,S9>=250,S9<=1000),"OK","ERROR") -> OK

Sheet Gear
A1: Gear
A2: Девять абстрактных предметов для трёх обязательных слотов
A3: Каждый предмет имеет одинаковый NormalizedValue в контрольном режиме. Прямые bonus_vs_animal запрещены.
A5: Gear ID | B5: Display Name RU | C5: Slot | D5: Stat 1 | E5: Operation 1 | F5: Value 1 | G5: Stat 2 | H5: Operation 2 | I5: Value 2 | J5: Tags | K5: Normalized Value FP | L5: Status | M5: Validation | N5: Notes RU | O5: Priority
A6: gear_offense_power_wraps | B6: Силовые бинты | C6: Offense | D6: Power | E6: Add | F6: 12 | H6: Add | I6: 0 | J6: power|strike | K6: 1000 | L6: Hypothesis | M6: =IF(AND(A6<>"",OR(C6="Offense",C6="Defense",C6="Utility"),D6<>"",K6>0),"OK","ERROR") -> OK | N6: Базовый урон без видового бонуса. | O6: 0
A7: gear_offense_precision_lens | B7: Прицельный визор | C7: Offense | D7: Precision | E7: Add | F7: 15 | H7: Add | I7: 0 | J7: precision|anti_dodge | K7: 1000 | L7: Hypothesis | M7: =IF(AND(A7<>"",OR(C7="Offense",C7="Defense",C7="Utility"),D7<>"",K7>0),"OK","ERROR") -> OK | N7: Контрplay активному Dodge через рейтинг. | O7: 0
A8: gear_offense_guardbreaker | B8: Накладки пробоя | C8: Offense | D8: GuardBreak | E8: Add | F8: 15 | H8: Add | I8: 0 | J8: guard_break|anti_block | K8: 1000 | L8: Hypothesis | M8: =IF(AND(A8<>"",OR(C8="Offense",C8="Defense",C8="Utility"),D8<>"",K8>0),"OK","ERROR") -> OK | N8: Не читает вид соперника. | O8: 0
A9: gear_defense_vital_harness | B9: Жизненный пояс | C9: Defense | D9: MaxHealth | E9: Add | F9: 120 | H9: Add | I9: 0 | J9: health|survival | K9: 1000 | L9: Hypothesis | M9: =IF(AND(A9<>"",OR(C9="Offense",C9="Defense",C9="Utility"),D9<>"",K9>0),"OK","ERROR") -> OK | N9: Прямая выживаемость. | O9: 0
A10: gear_defense_reinforced_hide | B10: Укреплённая защита | C10: Defense | D10: Armor | E10: Add | F10: 18 | H10: Add | I10: 0 | J10: armor|anti_multi_hit | K10: 1000 | L10: Hypothesis | M10: =IF(AND(A10<>"",OR(C10="Offense",C10="Defense",C10="Utility"),D10<>"",K10>0),"OK","ERROR") -> OK | N10: Особенно заметна против серий. | O10: 0
A11: gear_defense_control_brace | B11: Стабилизатор контроля | C11: Defense | D11: ControlResistance | E11: Add | F11: 18 | H11: Add | I11: 0 | J11: control_resistance|anti_control | K11: 1000 | L11: Hypothesis | M11: =IF(AND(A11<>"",OR(C11="Offense",C11="Defense",C11="Utility"),D11<>"",K11>0),"OK","ERROR") -> OK | N11: Сокращает stagger/hard control через формулу. | O11: 0
A12: gear_utility_sprint_soles | B12: Скоростные подошвы | C12: Utility | D12: MoveSpeed | E12: Add | F12: 12 | H12: Add | I12: 0 | J12: movement|position | K12: 1000 | L12: Hypothesis | M12: =IF(AND(A12<>"",OR(C12="Offense",C12="Defense",C12="Utility"),D12<>"",K12>0),"OK","ERROR") -> OK | N12: Улучшает добровольное движение. | O12: 0
A13: gear_utility_quickening_cord | B13: Шнур ускорения | C13: Utility | D13: ActionSpeed | E13: Add | F13: 12 | H13: Add | I13: 0 | J13: action_speed|tempo | K13: 1000 | L13: Hypothesis | M13: =IF(AND(A13<>"",OR(C13="Offense",C13="Defense",C13="Utility"),D13<>"",K13>0),"OK","ERROR") -> OK | N13: Изменяет startup/recovery в пределах action min/max. | O13: 0
A14: gear_utility_energy_cell | B14: Энергетический модуль | C14: Utility | D14: MaxEnergy | E14: Add | F14: 120 | G14: EnergyRegen | H14: Add | I14: 2 | J14: energy|resource_economy | K14: 1000 | L14: Hypothesis | M14: =IF(AND(A14<>"",OR(C14="Offense",C14="Defense",C14="Utility"),D14<>"",K14>0),"OK","ERROR") -> OK | N14: Не изменяет уникальный ресурс напрямую. | O14: 0

Sheet Test Builds
A1: Test Builds
A2: Двенадцать контрольных сборок для baseline, контрматчапов и signature usage
A3: Валидация проверяет 2 разных Special своего животного, 1 Passive, три правильных gear slot и существующую тактику.
A5: Build ID | B5: Display Name RU | C5: Animal ID | D5: Special 1 | E5: Special 2 | F5: Passive | G5: Offense Gear | H5: Defense Gear | I5: Utility Gear | J5: Tactic ID | K5: Power Band | L5: Intended Matchup | M5: Status | N5: Validation | O5: Notes RU
A6: build_bear_default | B6: Медведь — базовый | C6: bear | D6: bear_rampage_charge | E6: bear_earthbreaker | F6: bear_thick_hide | G6: gear_offense_power_wraps | H6: gear_defense_reinforced_hide | I6: gear_utility_energy_cell | J6: tactic_pressure | K6: Normalized 1000 | L6: baseline | M6: Hypothesis | N6: =IF(AND(D6<>E6,COUNTIFS(Actions!$A$6:$A$29,D6,Actions!$B$6:$B$29,C6,Actions!$D$6:$D$29,"Special")=1,COUNTIFS(Actions!$A$6:$A$29,E6,Actions!$B$6:$B$29,C6,Actions!$D$6:$D$29,"Special")=1,COUNTIFS(Passives!$A$6:$A$11,F6,Passives!$B$6:$B$11,C6)=1,COUNTIFS(Gear!$A$6:$A$14,G6,Gear!$C$6:$C$14,"Offense")=1,COUNTIFS(Gear!$A$6:$A$14,H6,Gear!$C$6:$C$14,"Defense")=1,COUNTIFS(Gear!$A$6:$A$14,I6,Gear!$C$6:$C$14,"Utility")=1,COUNTIF(Tactics!$A$6:$A$9,J6)=1),"OK","ERROR") -> OK | O6: Контрольная сборка первого пакетного запуска.
A7: build_bear_anti_kite | B7: Медведь — против дистанции | C7: bear | D7: bear_rampage_charge | E7: bear_fury_maul | F7: bear_pressure_fuels_rage | G7: gear_offense_precision_lens | H7: gear_defense_vital_harness | I7: gear_utility_sprint_soles | J7: tactic_position | K7: Normalized 1000 | L7: vs_kangaroo | M7: Hypothesis | N7: =IF(AND(D7<>E7,COUNTIFS(Actions!$A$6:$A$29,D7,Actions!$B$6:$B$29,C7,Actions!$D$6:$D$29,"Special")=1,COUNTIFS(Actions!$A$6:$A$29,E7,Actions!$B$6:$B$29,C7,Actions!$D$6:$D$29,"Special")=1,COUNTIFS(Passives!$A$6:$A$11,F7,Passives!$B$6:$B$11,C7)=1,COUNTIFS(Gear!$A$6:$A$14,G7,Gear!$C$6:$C$14,"Offense")=1,COUNTIFS(Gear!$A$6:$A$14,H7,Gear!$C$6:$C$14,"Defense")=1,COUNTIFS(Gear!$A$6:$A$14,I7,Gear!$C$6:$C$14,"Utility")=1,COUNTIF(Tactics!$A$6:$A$9,J7)=1),"OK","ERROR") -> OK | O7: Сближение, Precision и реализация close window.
A8: build_bear_counter_heavy | B8: Медведь — ответный | C8: bear | D8: bear_earthbreaker | E8: bear_fury_maul | F8: bear_thick_hide | G8: gear_offense_guardbreaker | H8: gear_defense_control_brace | I8: gear_utility_energy_cell | J8: tactic_counter | K8: Normalized 1000 | L8: vs_gorilla | M8: Hypothesis | N8: =IF(AND(D8<>E8,COUNTIFS(Actions!$A$6:$A$29,D8,Actions!$B$6:$B$29,C8,Actions!$D$6:$D$29,"Special")=1,COUNTIFS(Actions!$A$6:$A$29,E8,Actions!$B$6:$B$29,C8,Actions!$D$6:$D$29,"Special")=1,COUNTIFS(Passives!$A$6:$A$11,F8,Passives!$B$6:$B$11,C8)=1,COUNTIFS(Gear!$A$6:$A$14,G8,Gear!$C$6:$C$14,"Offense")=1,COUNTIFS(Gear!$A$6:$A$14,H8,Gear!$C$6:$C$14,"Defense")=1,COUNTIFS(Gear!$A$6:$A$14,I8,Gear!$C$6:$C$14,"Utility")=1,COUNTIF(Tactics!$A$6:$A$9,J8)=1),"OK","ERROR") -> OK | O8: Проверяет, не блокирует ли grab/control comeback полностью.
A9: build_bear_signature | B9: Медведь — ярость | C9: bear | D9: bear_rampage_charge | E9: bear_fury_maul | F9: bear_pressure_fuels_rage | G9: gear_offense_power_wraps | H9: gear_defense_vital_harness | I9: gear_utility_energy_cell | J9: tactic_signature | K9: Normalized 1000 | L9: signature_usage | M9: Hypothesis | N9: =IF(AND(D9<>E9,COUNTIFS(Actions!$A$6:$A$29,D9,Actions!$B$6:$B$29,C9,Actions!$D$6:$D$29,"Special")=1,COUNTIFS(Actions!$A$6:$A$29,E9,Actions!$B$6:$B$29,C9,Actions!$D$6:$D$29,"Special")=1,COUNTIFS(Passives!$A$6:$A$11,F9,Passives!$B$6:$B$11,C9)=1,COUNTIFS(Gear!$A$6:$A$14,G9,Gear!$C$6:$C$14,"Offense")=1,COUNTIFS(Gear!$A$6:$A$14,H9,Gear!$C$6:$C$14,"Defense")=1,COUNTIFS(Gear!$A$6:$A$14,I9,Gear!$C$6:$C$14,"Utility")=1,COUNTIF(Tactics!$A$6:$A$9,J9)=1),"OK","ERROR") -> OK | O9: Измеряет opportunity debt и расход ярости.
A10: build_kangaroo_default | B10: Кенгуру — базовый | C10: kangaroo | D10: kangaroo_flying_kick | E10: kangaroo_tail_counter | F10: kangaroo_never_still | G10: gear_offense_precision_lens | H10: gear_defense_vital_harness | I10: gear_utility_sprint_soles | J10: tactic_position | K10: Normalized 1000 | L10: baseline | M10: Hypothesis | N10: =IF(AND(D10<>E10,COUNTIFS(Actions!$A$6:$A$29,D10,Actions!$B$6:$B$29,C10,Actions!$D$6:$D$29,"Special")=1,COUNTIFS(Actions!$A$6:$A$29,E10,Actions!$B$6:$B$29,C10,Actions!$D$6:$D$29,"Special")=1,COUNTIFS(Passives!$A$6:$A$11,F10,Passives!$B$6:$B$11,C10)=1,COUNTIFS(Gear!$A$6:$A$14,G10,Gear!$C$6:$C$14,"Offense")=1,COUNTIFS(Gear!$A$6:$A$14,H10,Gear!$C$6:$C$14,"Defense")=1,COUNTIFS(Gear!$A$6:$A$14,I10,Gear!$C$6:$C$14,"Utility")=1,COUNTIF(Tactics!$A$6:$A$9,J10)=1),"OK","ERROR") -> OK | O10: Контрольная сборка preferred mid range.
A11: build_kangaroo_anti_grab | B11: Кенгуру — против захвата | C11: kangaroo | D11: kangaroo_tail_counter | E11: kangaroo_tempo_barrage | F11: kangaroo_clean_rhythm | G11: gear_offense_power_wraps | H11: gear_defense_control_brace | I11: gear_utility_sprint_soles | J11: tactic_counter | K11: Normalized 1000 | L11: vs_gorilla | M11: Hypothesis | N11: =IF(AND(D11<>E11,COUNTIFS(Actions!$A$6:$A$29,D11,Actions!$B$6:$B$29,C11,Actions!$D$6:$D$29,"Special")=1,COUNTIFS(Actions!$A$6:$A$29,E11,Actions!$B$6:$B$29,C11,Actions!$D$6:$D$29,"Special")=1,COUNTIFS(Passives!$A$6:$A$11,F11,Passives!$B$6:$B$11,C11)=1,COUNTIFS(Gear!$A$6:$A$14,G11,Gear!$C$6:$C$14,"Offense")=1,COUNTIFS(Gear!$A$6:$A$14,H11,Gear!$C$6:$C$14,"Defense")=1,COUNTIFS(Gear!$A$6:$A$14,I11,Gear!$C$6:$C$14,"Utility")=1,COUNTIF(Tactics!$A$6:$A$9,J11)=1),"OK","ERROR") -> OK | O11: Проверяет контрplay grab/wall pressure.
A12: build_kangaroo_kite | B12: Кенгуру — дистанция | C12: kangaroo | D12: kangaroo_flying_kick | E12: kangaroo_tempo_barrage | F12: kangaroo_never_still | G12: gear_offense_precision_lens | H12: gear_defense_reinforced_hide | I12: gear_utility_quickening_cord | J12: tactic_position | K12: Normalized 1000 | L12: vs_bear | M12: Hypothesis | N12: =IF(AND(D12<>E12,COUNTIFS(Actions!$A$6:$A$29,D12,Actions!$B$6:$B$29,C12,Actions!$D$6:$D$29,"Special")=1,COUNTIFS(Actions!$A$6:$A$29,E12,Actions!$B$6:$B$29,C12,Actions!$D$6:$D$29,"Special")=1,COUNTIFS(Passives!$A$6:$A$11,F12,Passives!$B$6:$B$11,C12)=1,COUNTIFS(Gear!$A$6:$A$14,G12,Gear!$C$6:$C$14,"Offense")=1,COUNTIFS(Gear!$A$6:$A$14,H12,Gear!$C$6:$C$14,"Defense")=1,COUNTIFS(Gear!$A$6:$A$14,I12,Gear!$C$6:$C$14,"Utility")=1,COUNTIF(Tactics!$A$6:$A$9,J12)=1),"OK","ERROR") -> OK | O12: Проверяет отсутствие бесконечного kite.
A13: build_kangaroo_signature | B13: Кенгуру — темп | C13: kangaroo | D13: kangaroo_flying_kick | E13: kangaroo_tempo_barrage | F13: kangaroo_clean_rhythm | G13: gear_offense_power_wraps | H13: gear_defense_vital_harness | I13: gear_utility_energy_cell | J13: tactic_signature | K13: Normalized 1000 | L13: signature_usage | M13: Hypothesis | N13: =IF(AND(D13<>E13,COUNTIFS(Actions!$A$6:$A$29,D13,Actions!$B$6:$B$29,C13,Actions!$D$6:$D$29,"Special")=1,COUNTIFS(Actions!$A$6:$A$29,E13,Actions!$B$6:$B$29,C13,Actions!$D$6:$D$29,"Special")=1,COUNTIFS(Passives!$A$6:$A$11,F13,Passives!$B$6:$B$11,C13)=1,COUNTIFS(Gear!$A$6:$A$14,G13,Gear!$C$6:$C$14,"Offense")=1,COUNTIFS(Gear!$A$6:$A$14,H13,Gear!$C$6:$C$14,"Defense")=1,COUNTIFS(Gear!$A$6:$A$14,I13,Gear!$C$6:$C$14,"Utility")=1,COUNTIF(Tactics!$A$6:$A$9,J13)=1),"OK","ERROR") -> OK | O13: Измеряет Tempo tiers и частоту finisher.
A14: build_gorilla_default | B14: Горилла — базовый | C14: gorilla | D14: gorilla_pivot_throw | E14: gorilla_wall_breaker | F14: gorilla_territorial_pressure | G14: gear_offense_guardbreaker | H14: gear_defense_reinforced_hide | I14: gear_utility_energy_cell | J14: tactic_pressure | K14: Normalized 1000 | L14: baseline | M14: Hypothesis | N14: =IF(AND(D14<>E14,COUNTIFS(Actions!$A$6:$A$29,D14,Actions!$B$6:$B$29,C14,Actions!$D$6:$D$29,"Special")=1,COUNTIFS(Actions!$A$6:$A$29,E14,Actions!$B$6:$B$29,C14,Actions!$D$6:$D$29,"Special")=1,COUNTIFS(Passives!$A$6:$A$11,F14,Passives!$B$6:$B$11,C14)=1,COUNTIFS(Gear!$A$6:$A$14,G14,Gear!$C$6:$C$14,"Offense")=1,COUNTIFS(Gear!$A$6:$A$14,H14,Gear!$C$6:$C$14,"Defense")=1,COUNTIFS(Gear!$A$6:$A$14,I14,Gear!$C$6:$C$14,"Utility")=1,COUNTIF(Tactics!$A$6:$A$9,J14)=1),"OK","ERROR") -> OK | O14: Контрольная wall/grab сборка.
A15: build_gorilla_anti_heavy | B15: Горилла — против commit | C15: gorilla | D15: gorilla_pivot_throw | E15: gorilla_overhead_pound | F15: gorilla_iron_grip | G15: gear_offense_power_wraps | H15: gear_defense_control_brace | I15: gear_utility_quickening_cord | J15: tactic_counter | K15: Normalized 1000 | L15: vs_bear | M15: Hypothesis | N15: =IF(AND(D15<>E15,COUNTIFS(Actions!$A$6:$A$29,D15,Actions!$B$6:$B$29,C15,Actions!$D$6:$D$29,"Special")=1,COUNTIFS(Actions!$A$6:$A$29,E15,Actions!$B$6:$B$29,C15,Actions!$D$6:$D$29,"Special")=1,COUNTIFS(Passives!$A$6:$A$11,F15,Passives!$B$6:$B$11,C15)=1,COUNTIFS(Gear!$A$6:$A$14,G15,Gear!$C$6:$C$14,"Offense")=1,COUNTIFS(Gear!$A$6:$A$14,H15,Gear!$C$6:$C$14,"Defense")=1,COUNTIFS(Gear!$A$6:$A$14,I15,Gear!$C$6:$C$14,"Utility")=1,COUNTIF(Tactics!$A$6:$A$9,J15)=1),"OK","ERROR") -> OK | O15: Захват тяжёлого commit и punish control window.
A16: build_gorilla_wall_pressure | B16: Горилла — стена | C16: gorilla | D16: gorilla_pivot_throw | E16: gorilla_wall_breaker | F16: gorilla_territorial_pressure | G16: gear_offense_guardbreaker | H16: gear_defense_vital_harness | I16: gear_utility_sprint_soles | J16: tactic_position | K16: Normalized 1000 | L16: vs_kangaroo | M16: Hypothesis | N16: =IF(AND(D16<>E16,COUNTIFS(Actions!$A$6:$A$29,D16,Actions!$B$6:$B$29,C16,Actions!$D$6:$D$29,"Special")=1,COUNTIFS(Actions!$A$6:$A$29,E16,Actions!$B$6:$B$29,C16,Actions!$D$6:$D$29,"Special")=1,COUNTIFS(Passives!$A$6:$A$11,F16,Passives!$B$6:$B$11,C16)=1,COUNTIFS(Gear!$A$6:$A$14,G16,Gear!$C$6:$C$14,"Offense")=1,COUNTIFS(Gear!$A$6:$A$14,H16,Gear!$C$6:$C$14,"Defense")=1,COUNTIFS(Gear!$A$6:$A$14,I16,Gear!$C$6:$C$14,"Utility")=1,COUNTIF(Tactics!$A$6:$A$9,J16)=1),"OK","ERROR") -> OK | O16: Проверяет резкость переворота у стены.
A17: build_gorilla_signature | B17: Горилла — хватка | C17: gorilla | D17: gorilla_overhead_pound | E17: gorilla_wall_breaker | F17: gorilla_iron_grip | G17: gear_offense_power_wraps | H17: gear_defense_reinforced_hide | I17: gear_utility_energy_cell | J17: tactic_signature | K17: Normalized 1000 | L17: signature_usage | M17: Hypothesis | N17: =IF(AND(D17<>E17,COUNTIFS(Actions!$A$6:$A$29,D17,Actions!$B$6:$B$29,C17,Actions!$D$6:$D$29,"Special")=1,COUNTIFS(Actions!$A$6:$A$29,E17,Actions!$B$6:$B$29,C17,Actions!$D$6:$D$29,"Special")=1,COUNTIFS(Passives!$A$6:$A$11,F17,Passives!$B$6:$B$11,C17)=1,COUNTIFS(Gear!$A$6:$A$14,G17,Gear!$C$6:$C$14,"Offense")=1,COUNTIFS(Gear!$A$6:$A$14,H17,Gear!$C$6:$C$14,"Defense")=1,COUNTIFS(Gear!$A$6:$A$14,I17,Gear!$C$6:$C$14,"Utility")=1,COUNTIF(Tactics!$A$6:$A$9,J17)=1),"OK","ERROR") -> OK | O17: Измеряет Grip tiers и legal wall opportunities.

Sheet Expected Matchups
A1: Expected Matchups
A2: Направленные целевые диапазоны для RPS-гипотезы и зеркал
A3: Это не видовые коэффициенты урона. Диапазоны служат критерием пакетного теста одинаковой нормализованной силы.
A5: Matchup ID | B5: Animal A | C5: Animal B | D5: Target Win Rate A | E5: Min Win Rate A | F5: Max Win Rate A | G5: Draw Rate Max | H5: Timeout Rate Max | I5: Duration Min Sec | J5: Duration Max Sec | K5: Signature Use Min | L5: Signature Use Max | M5: Expected Edge | N5: Control Build A | O5: Control Build B | P5: Hypothesis RU | Q5: Risk RU | R5: Status | S5: Validation
A6: bear_vs_bear | B6: bear | C6: bear | D6: 0.5 | E6: 0.47 | F6: 0.53 | G6: 0.02 | H6: 0.02 | I6: 35 | J6: 60 | K6: 0.15 | L6: 0.35 | M6: Neutral | N6: build_bear_default | O6: build_bear_default | P6: Зеркало нейтрально; side и seed не дают системного перевеса. | Q6: Повторяющиеся heavy/Block циклы. | R6: Hypothesis | S6: =IF(AND(D6>=E6,D6<=F6,E6<=F6,G6<=0.02,H6<=0.02,I6<J6,K6<=L6,COUNTIF('Test Builds'!$A$6:$A$17,N6)=1,COUNTIF('Test Builds'!$A$6:$A$17,O6)=1),"OK","ERROR") -> OK
A7: bear_vs_kangaroo | B7: bear | C7: kangaroo | D7: 0.53 | E7: 0.5 | F7: 0.56 | G7: 0.02 | H7: 0.02 | I7: 35 | J7: 60 | K7: 0.15 | L7: 0.35 | M7: Small A edge | N7: build_bear_default | O7: build_kangaroo_default | P7: Медведь слегка выигрывает при успешном сближении. | Q7: Кенгуру либо бесконечно kite, либо не имеет контрplay. | R7: Hypothesis | S7: =IF(AND(D7>=E7,D7<=F7,E7<=F7,G7<=0.02,H7<=0.02,I7<J7,K7<=L7,COUNTIF('Test Builds'!$A$6:$A$17,N7)=1,COUNTIF('Test Builds'!$A$6:$A$17,O7)=1),"OK","ERROR") -> OK
A8: bear_vs_gorilla | B8: bear | C8: gorilla | D8: 0.47 | E8: 0.44 | F8: 0.5 | G8: 0.02 | H8: 0.02 | I8: 35 | J8: 60 | K8: 0.15 | L8: 0.35 | M8: Small B edge | N8: build_bear_default | O8: build_gorilla_default | P8: Горилла слегка наказывает тяжёлые commit захватом. | Q8: Контроль полностью блокирует rage comeback. | R8: Hypothesis | S8: =IF(AND(D8>=E8,D8<=F8,E8<=F8,G8<=0.02,H8<=0.02,I8<J8,K8<=L8,COUNTIF('Test Builds'!$A$6:$A$17,N8)=1,COUNTIF('Test Builds'!$A$6:$A$17,O8)=1),"OK","ERROR") -> OK
A9: kangaroo_vs_bear | B9: kangaroo | C9: bear | D9: 0.47 | E9: 0.44 | F9: 0.5 | G9: 0.02 | H9: 0.02 | I9: 35 | J9: 60 | K9: 0.15 | L9: 0.35 | M9: Small B edge | N9: build_kangaroo_default | O9: build_bear_default | P9: Направленная обратная строка для side-bias теста. | Q9: Результат не должен отличаться от инверсии больше статистического шума. | R9: Hypothesis | S9: =IF(AND(D9>=E9,D9<=F9,E9<=F9,G9<=0.02,H9<=0.02,I9<J9,K9<=L9,COUNTIF('Test Builds'!$A$6:$A$17,N9)=1,COUNTIF('Test Builds'!$A$6:$A$17,O9)=1),"OK","ERROR") -> OK
A10: kangaroo_vs_kangaroo | B10: kangaroo | C10: kangaroo | D10: 0.5 | E10: 0.47 | F10: 0.53 | G10: 0.02 | H10: 0.02 | I10: 35 | J10: 60 | K10: 0.15 | L10: 0.35 | M10: Neutral | N10: build_kangaroo_default | O10: build_kangaroo_default | P10: Зеркало нейтрально и не сводится к бесконечному движению. | Q10: Слишком много timeout или одинаковых n-gram. | R10: Hypothesis | S10: =IF(AND(D10>=E10,D10<=F10,E10<=F10,G10<=0.02,H10<=0.02,I10<J10,K10<=L10,COUNTIF('Test Builds'!$A$6:$A$17,N10)=1,COUNTIF('Test Builds'!$A$6:$A$17,O10)=1),"OK","ERROR") -> OK
A11: kangaroo_vs_gorilla | B11: kangaroo | C11: gorilla | D11: 0.53 | E11: 0.5 | F11: 0.56 | G11: 0.02 | H11: 0.02 | I11: 35 | J11: 60 | K11: 0.15 | L11: 0.35 | M11: Small A edge | N11: build_kangaroo_default | O11: build_gorilla_default | P11: Кенгуру слегка выигрывает на открытой дистанции. | Q11: Wall pressure слишком резко переворачивает бой. | R11: Hypothesis | S11: =IF(AND(D11>=E11,D11<=F11,E11<=F11,G11<=0.02,H11<=0.02,I11<J11,K11<=L11,COUNTIF('Test Builds'!$A$6:$A$17,N11)=1,COUNTIF('Test Builds'!$A$6:$A$17,O11)=1),"OK","ERROR") -> OK
A12: gorilla_vs_bear | B12: gorilla | C12: bear | D12: 0.53 | E12: 0.5 | F12: 0.56 | G12: 0.02 | H12: 0.02 | I12: 35 | J12: 60 | K12: 0.15 | L12: 0.35 | M12: Small A edge | N12: build_gorilla_default | O12: build_bear_default | P12: Направленная обратная строка для side-bias теста. | Q12: Grab priority создаёт слишком жёсткий lock. | R12: Hypothesis | S12: =IF(AND(D12>=E12,D12<=F12,E12<=F12,G12<=0.02,H12<=0.02,I12<J12,K12<=L12,COUNTIF('Test Builds'!$A$6:$A$17,N12)=1,COUNTIF('Test Builds'!$A$6:$A$17,O12)=1),"OK","ERROR") -> OK
A13: gorilla_vs_kangaroo | B13: gorilla | C13: kangaroo | D13: 0.47 | E13: 0.44 | F13: 0.5 | G13: 0.02 | H13: 0.02 | I13: 35 | J13: 60 | K13: 0.15 | L13: 0.35 | M13: Small B edge | N13: build_gorilla_default | O13: build_kangaroo_default | P13: Направленная обратная строка для side-bias теста. | Q13: Горилла не получает legal wall opportunity. | R13: Hypothesis | S13: =IF(AND(D13>=E13,D13<=F13,E13<=F13,G13<=0.02,H13<=0.02,I13<J13,K13<=L13,COUNTIF('Test Builds'!$A$6:$A$17,N13)=1,COUNTIF('Test Builds'!$A$6:$A$17,O13)=1),"OK","ERROR") -> OK
A14: gorilla_vs_gorilla | B14: gorilla | C14: gorilla | D14: 0.5 | E14: 0.47 | F14: 0.53 | G14: 0.02 | H14: 0.02 | I14: 35 | J14: 60 | K14: 0.15 | L14: 0.35 | M14: Neutral | N14: build_gorilla_default | O14: build_gorilla_default | P14: Зеркало нейтрально, grab conflict разрешается без side order. | Q14: Block/grab loop и высокая доля hard control. | R14: Hypothesis | S14: =IF(AND(D14>=E14,D14<=F14,E14<=F14,G14<=0.02,H14<=0.02,I14<J14,K14<=L14,COUNTIF('Test Builds'!$A$6:$A$17,N14)=1,COUNTIF('Test Builds'!$A$6:$A$17,O14)=1),"OK","ERROR") -> OK

Sheet Batch Results
A1: Batch Results
A2: Шаблон результатов девяти направленных matchup seed sweeps
A3: Wins A + Wins B + Draws — валидные бои. Timeouts — подмножество исходов, Invalid считается отдельно. Детализация действий остаётся в CSV Combat Lab.
A5: Run ID | B5: Run Status | C5: Config Version | D5: Engine Version | E5: Config Hash | F5: Seed Start | G5: Battle Count | H5: Build A | I5: Build B | J5: Animal A | K5: Animal B | L5: Wins A | M5: Wins B | N5: Draws | O5: Timeouts | P5: Invalid | Q5: Win Rate A | R5: Draw Rate | S5: Timeout Rate | T5: Avg Duration Sec | U5: Median Duration Sec | V5: P10 Duration Sec | W5: P90 Duration Sec | X5: Avg Winner HP % | Y5: Signature Usage A | Z5: Signature Usage B | AA5: Control Time A Sec | AB5: Control Time B Sec | AC5: Wall Impact Rate | AD5: Comeback Rate | AE5: Repeated N-gram Rate | AF5: Determinism Failures | AG5: Explainability Failures | AH5: Matchup ID | AI5: Expected Min | AJ5: Expected Max | AK5: Expected Timeout Max | AL5: Result Status | AM5: Notes RU
A6: run_v01_01 | B6: Planned | C6: v0.1 | F6: 1 | G6: 10000 | H6: build_bear_default | I6: build_bear_default | J6: =IFERROR(VLOOKUP(H6,'Test Builds'!$A$6:$C$17,3,FALSE),"") -> bear | K6: =IFERROR(VLOOKUP(I6,'Test Builds'!$A$6:$C$17,3,FALSE),"") -> bear | Q6: =IF(SUM(L6:N6)=0,"",L6/SUM(L6:N6)) | R6: =IF(SUM(L6:N6)=0,"",N6/SUM(L6:N6)) | S6: =IF(SUM(L6:N6)=0,"",O6/SUM(L6:N6)) | AH6: =J6&"_vs_"&K6 -> bear_vs_bear | AI6: =IFERROR(VLOOKUP(AH6,'Expected Matchups'!$A$6:$H$14,5,FALSE),"") -> 0.47 | AJ6: =IFERROR(VLOOKUP(AH6,'Expected Matchups'!$A$6:$H$14,6,FALSE),"") -> 0.53 | AK6: =IFERROR(VLOOKUP(AH6,'Expected Matchups'!$A$6:$H$14,8,FALSE),"") -> 0.02 | AL6: =IF(SUM(L6:N6)=0,"PENDING",IF(OR(AF6>0,AG6>0),"ERROR",IF(AND(Q6>=AI6,Q6<=AJ6,S6<=AK6,P6=0),"PASS","REVIEW"))) -> PENDING | AM6: Плановый seed sweep; заполнить агрегаты из Combat Lab.
A7: run_v01_02 | B7: Planned | C7: v0.1 | F7: 10001 | G7: 10000 | H7: build_bear_default | I7: build_kangaroo_default | J7: =IFERROR(VLOOKUP(H7,'Test Builds'!$A$6:$C$17,3,FALSE),"") -> bear | K7: =IFERROR(VLOOKUP(I7,'Test Builds'!$A$6:$C$17,3,FALSE),"") -> kangaroo | Q7: =IF(SUM(L7:N7)=0,"",L7/SUM(L7:N7)) | R7: =IF(SUM(L7:N7)=0,"",N7/SUM(L7:N7)) | S7: =IF(SUM(L7:N7)=0,"",O7/SUM(L7:N7)) | AH7: =J7&"_vs_"&K7 -> bear_vs_kangaroo | AI7: =IFERROR(VLOOKUP(AH7,'Expected Matchups'!$A$6:$H$14,5,FALSE),"") -> 0.5 | AJ7: =IFERROR(VLOOKUP(AH7,'Expected Matchups'!$A$6:$H$14,6,FALSE),"") -> 0.56 | AK7: =IFERROR(VLOOKUP(AH7,'Expected Matchups'!$A$6:$H$14,8,FALSE),"") -> 0.02 | AL7: =IF(SUM(L7:N7)=0,"PENDING",IF(OR(AF7>0,AG7>0),"ERROR",IF(AND(Q7>=AI7,Q7<=AJ7,S7<=AK7,P7=0),"PASS","REVIEW"))) -> PENDING | AM7: Плановый seed sweep; заполнить агрегаты из Combat Lab.
A8: run_v01_03 | B8: Planned | C8: v0.1 | F8: 20001 | G8: 10000 | H8: build_bear_default | I8: build_gorilla_default | J8: =IFERROR(VLOOKUP(H8,'Test Builds'!$A$6:$C$17,3,FALSE),"") -> bear | K8: =IFERROR(VLOOKUP(I8,'Test Builds'!$A$6:$C$17,3,FALSE),"") -> gorilla | Q8: =IF(SUM(L8:N8)=0,"",L8/SUM(L8:N8)) | R8: =IF(SUM(L8:N8)=0,"",N8/SUM(L8:N8)) | S8: =IF(SUM(L8:N8)=0,"",O8/SUM(L8:N8)) | AH8: =J8&"_vs_"&K8 -> bear_vs_gorilla | AI8: =IFERROR(VLOOKUP(AH8,'Expected Matchups'!$A$6:$H$14,5,FALSE),"") -> 0.44 | AJ8: =IFERROR(VLOOKUP(AH8,'Expected Matchups'!$A$6:$H$14,6,FALSE),"") -> 0.5 | AK8: =IFERROR(VLOOKUP(AH8,'Expected Matchups'!$A$6:$H$14,8,FALSE),"") -> 0.02 | AL8: =IF(SUM(L8:N8)=0,"PENDING",IF(OR(AF8>0,AG8>0),"ERROR",IF(AND(Q8>=AI8,Q8<=AJ8,S8<=AK8,P8=0),"PASS","REVIEW"))) -> PENDING | AM8: Плановый seed sweep; заполнить агрегаты из Combat Lab.
A9: run_v01_04 | B9: Planned | C9: v0.1 | F9: 30001 | G9: 10000 | H9: build_kangaroo_default | I9: build_bear_default | J9: =IFERROR(VLOOKUP(H9,'Test Builds'!$A$6:$C$17,3,FALSE),"") -> kangaroo | K9: =IFERROR(VLOOKUP(I9,'Test Builds'!$A$6:$C$17,3,FALSE),"") -> bear | Q9: =IF(SUM(L9:N9)=0,"",L9/SUM(L9:N9)) | R9: =IF(SUM(L9:N9)=0,"",N9/SUM(L9:N9)) | S9: =IF(SUM(L9:N9)=0,"",O9/SUM(L9:N9)) | AH9: =J9&"_vs_"&K9 -> kangaroo_vs_bear | AI9: =IFERROR(VLOOKUP(AH9,'Expected Matchups'!$A$6:$H$14,5,FALSE),"") -> 0.44 | AJ9: =IFERROR(VLOOKUP(AH9,'Expected Matchups'!$A$6:$H$14,6,FALSE),"") -> 0.5 | AK9: =IFERROR(VLOOKUP(AH9,'Expected Matchups'!$A$6:$H$14,8,FALSE),"") -> 0.02 | AL9: =IF(SUM(L9:N9)=0,"PENDING",IF(OR(AF9>0,AG9>0),"ERROR",IF(AND(Q9>=AI9,Q9<=AJ9,S9<=AK9,P9=0),"PASS","REVIEW"))) -> PENDING | AM9: Плановый seed sweep; заполнить агрегаты из Combat Lab.
A10: run_v01_05 | B10: Planned | C10: v0.1 | F10: 40001 | G10: 10000 | H10: build_kangaroo_default | I10: build_kangaroo_default | J10: =IFERROR(VLOOKUP(H10,'Test Builds'!$A$6:$C$17,3,FALSE),"") -> kangaroo | K10: =IFERROR(VLOOKUP(I10,'Test Builds'!$A$6:$C$17,3,FALSE),"") -> kangaroo | Q10: =IF(SUM(L10:N10)=0,"",L10/SUM(L10:N10)) | R10: =IF(SUM(L10:N10)=0,"",N10/SUM(L10:N10)) | S10: =IF(SUM(L10:N10)=0,"",O10/SUM(L10:N10)) | AH10: =J10&"_vs_"&K10 -> kangaroo_vs_kangaroo | AI10: =IFERROR(VLOOKUP(AH10,'Expected Matchups'!$A$6:$H$14,5,FALSE),"") -> 0.47 | AJ10: =IFERROR(VLOOKUP(AH10,'Expected Matchups'!$A$6:$H$14,6,FALSE),"") -> 0.53 | AK10: =IFERROR(VLOOKUP(AH10,'Expected Matchups'!$A$6:$H$14,8,FALSE),"") -> 0.02 | AL10: =IF(SUM(L10:N10)=0,"PENDING",IF(OR(AF10>0,AG10>0),"ERROR",IF(AND(Q10>=AI10,Q10<=AJ10,S10<=AK10,P10=0),"PASS","REVIEW"))) -> PENDING | AM10: Плановый seed sweep; заполнить агрегаты из Combat Lab.
A11: run_v01_06 | B11: Planned | C11: v0.1 | F11: 50001 | G11: 10000 | H11: build_kangaroo_default | I11: build_gorilla_default | J11: =IFERROR(VLOOKUP(H11,'Test Builds'!$A$6:$C$17,3,FALSE),"") -> kangaroo | K11: =IFERROR(VLOOKUP(I11,'Test Builds'!$A$6:$C$17,3,FALSE),"") -> gorilla | Q11: =IF(SUM(L11:N11)=0,"",L11/SUM(L11:N11)) | R11: =IF(SUM(L11:N11)=0,"",N11/SUM(L11:N11)) | S11: =IF(SUM(L11:N11)=0,"",O11/SUM(L11:N11)) | AH11: =J11&"_vs_"&K11 -> kangaroo_vs_gorilla | AI11: =IFERROR(VLOOKUP(AH11,'Expected Matchups'!$A$6:$H$14,5,FALSE),"") -> 0.5 | AJ11: =IFERROR(VLOOKUP(AH11,'Expected Matchups'!$A$6:$H$14,6,FALSE),"") -> 0.56 | AK11: =IFERROR(VLOOKUP(AH11,'Expected Matchups'!$A$6:$H$14,8,FALSE),"") -> 0.02 | AL11: =IF(SUM(L11:N11)=0,"PENDING",IF(OR(AF11>0,AG11>0),"ERROR",IF(AND(Q11>=AI11,Q11<=AJ11,S11<=AK11,P11=0),"PASS","REVIEW"))) -> PENDING | AM11: Плановый seed sweep; заполнить агрегаты из Combat Lab.
A12: run_v01_07 | B12: Planned | C12: v0.1 | F12: 60001 | G12: 10000 | H12: build_gorilla_default | I12: build_bear_default | J12: =IFERROR(VLOOKUP(H12,'Test Builds'!$A$6:$C$17,3,FALSE),"") -> gorilla | K12: =IFERROR(VLOOKUP(I12,'Test Builds'!$A$6:$C$17,3,FALSE),"") -> bear | Q12: =IF(SUM(L12:N12)=0,"",L12/SUM(L12:N12)) | R12: =IF(SUM(L12:N12)=0,"",N12/SUM(L12:N12)) | S12: =IF(SUM(L12:N12)=0,"",O12/SUM(L12:N12)) | AH12: =J12&"_vs_"&K12 -> gorilla_vs_bear | AI12: =IFERROR(VLOOKUP(AH12,'Expected Matchups'!$A$6:$H$14,5,FALSE),"") -> 0.5 | AJ12: =IFERROR(VLOOKUP(AH12,'Expected Matchups'!$A$6:$H$14,6,FALSE),"") -> 0.56 | AK12: =IFERROR(VLOOKUP(AH12,'Expected Matchups'!$A$6:$H$14,8,FALSE),"") -> 0.02 | AL12: =IF(SUM(L12:N12)=0,"PENDING",IF(OR(AF12>0,AG12>0),"ERROR",IF(AND(Q12>=AI12,Q12<=AJ12,S12<=AK12,P12=0),"PASS","REVIEW"))) -> PENDING | AM12: Плановый seed sweep; заполнить агрегаты из Combat Lab.
A13: run_v01_08 | B13: Planned | C13: v0.1 | F13: 70001 | G13: 10000 | H13: build_gorilla_default | I13: build_kangaroo_default | J13: =IFERROR(VLOOKUP(H13,'Test Builds'!$A$6:$C$17,3,FALSE),"") -> gorilla | K13: =IFERROR(VLOOKUP(I13,'Test Builds'!$A$6:$C$17,3,FALSE),"") -> kangaroo | Q13: =IF(SUM(L13:N13)=0,"",L13/SUM(L13:N13)) | R13: =IF(SUM(L13:N13)=0,"",N13/SUM(L13:N13)) | S13: =IF(SUM(L13:N13)=0,"",O13/SUM(L13:N13)) | AH13: =J13&"_vs_"&K13 -> gorilla_vs_kangaroo | AI13: =IFERROR(VLOOKUP(AH13,'Expected Matchups'!$A$6:$H$14,5,FALSE),"") -> 0.44 | AJ13: =IFERROR(VLOOKUP(AH13,'Expected Matchups'!$A$6:$H$14,6,FALSE),"") -> 0.5 | AK13: =IFERROR(VLOOKUP(AH13,'Expected Matchups'!$A$6:$H$14,8,FALSE),"") -> 0.02 | AL13: =IF(SUM(L13:N13)=0,"PENDING",IF(OR(AF13>0,AG13>0),"ERROR",IF(AND(Q13>=AI13,Q13<=AJ13,S13<=AK13,P13=0),"PASS","REVIEW"))) -> PENDING | AM13: Плановый seed sweep; заполнить агрегаты из Combat Lab.
A14: run_v01_09 | B14: Planned | C14: v0.1 | F14: 80001 | G14: 10000 | H14: build_gorilla_default | I14: build_gorilla_default | J14: =IFERROR(VLOOKUP(H14,'Test Builds'!$A$6:$C$17,3,FALSE),"") -> gorilla | K14: =IFERROR(VLOOKUP(I14,'Test Builds'!$A$6:$C$17,3,FALSE),"") -> gorilla | Q14: =IF(SUM(L14:N14)=0,"",L14/SUM(L14:N14)) | R14: =IF(SUM(L14:N14)=0,"",N14/SUM(L14:N14)) | S14: =IF(SUM(L14:N14)=0,"",O14/SUM(L14:N14)) | AH14: =J14&"_vs_"&K14 -> gorilla_vs_gorilla | AI14: =IFERROR(VLOOKUP(AH14,'Expected Matchups'!$A$6:$H$14,5,FALSE),"") -> 0.47 | AJ14: =IFERROR(VLOOKUP(AH14,'Expected Matchups'!$A$6:$H$14,6,FALSE),"") -> 0.53 | AK14: =IFERROR(VLOOKUP(AH14,'Expected Matchups'!$A$6:$H$14,8,FALSE),"") -> 0.02 | AL14: =IF(SUM(L14:N14)=0,"PENDING",IF(OR(AF14>0,AG14>0),"ERROR",IF(AND(Q14>=AI14,Q14<=AJ14,S14<=AK14,P14=0),"PASS","REVIEW"))) -> PENDING | AM14: Плановый seed sweep; заполнить агрегаты из Combat Lab.

Sheet Change Log
A1: Change Log
A2: История существенных изменений параметров и гипотез
A3: Каждый утверждённый balance pass создаёт новую запись и повышает ConfigVersion. Мелкие редакционные правки можно объединять.
A5: Change ID | B5: Version | C5: Date | D5: Status | E5: Owner | F5: Sheets | G5: Decision | H5: Reason | I5: Related Hypothesis
A6: CHG-0001 | B6: v0.1 | C6: 46232 | D6: Draft | E6: Game Designer / Founder / Product Owner | F6: All | G6: Создан стартовый Combat Balance Workbook по CDS v0.1. | H6: Дать Combat Lab единый источник всех числовых параметров и тестовых ожиданий. | I6: HYP-01; HYP-02; HYP-03; HYP-04; DATA-01

Sheet JSON Map
A1: JSON Export Map
A2: Живая нормализованная карта source cell → canonical JSON property
A3: Экспортёр сортирует строки по SortOrder, группирует Namespace/ObjectId, приводит Live Value по ValueType и отклоняет любой Validation=ERROR. Live Value обновляется формулами при редактировании источника.
A5: Sort Order | B5: Namespace | C5: Object ID | D5: Property Path | E5: Value Type | F5: Live Value | G5: Unit | H5: Source Sheet | I5: Source Cell | J5: Required | K5: Include Runtime | L5: Validation | M5: Notes RU
A6: 1 | B6: global | C6: root | D6: global.sim.schema_version | E6: string | F6: ='Global Config'!D6 -> combat.balance/0.2 | G6: id | H6: Global Config | I6: D6 | J6: TRUE | K6: TRUE | L6: ='Global Config'!K6 -> OK | M6: Версия схемы баланса
A7: 2 | B7: global | C7: root | D7: global.sim.config_version | E7: string | F7: ='Global Config'!D7 -> v0.2 | G7: id | H7: Global Config | I7: D7 | J7: TRUE | K7: TRUE | L7: ='Global Config'!K7 -> OK | M7: Версия набора параметров
A8: 3 | B8: global | C8: root | D8: global.sim.rng_version | E8: string | F8: ='Global Config'!D8 -> pcg32/1 | G8: id | H8: Global Config | I8: D8 | J8: TRUE | K8: TRUE | L8: ='Global Config'!K8 -> OK | M8: Версия алгоритма RNG
A9: 4 | B9: global | C9: root | D9: global.sim.ordering_version | E9: string | F9: ='Global Config'!D9 -> tick-pipeline/1 | G9: id | H9: Global Config | I9: D9 | J9: TRUE | K9: TRUE | L9: ='Global Config'!K9 -> OK | M9: Версия порядка тика
A10: 5 | B10: global | C10: root | D10: global.sim.tick_ms | E10: int | F10: ='Global Config'!D10 -> 100 | G10: ms | H10: Global Config | I10: D10 | J10: TRUE | K10: TRUE | L10: ='Global Config'!K10 -> OK | M10: Длительность одного тика
A11: 6 | B11: global | C11: root | D11: battle.time_limit_ticks | E11: int | F11: ='Global Config'!D11 -> 600 | G11: ticks | H11: Global Config | I11: D11 | J11: TRUE | K11: TRUE | L11: ='Global Config'!K11 -> OK | M11: Лимит боя
A12: 7 | B12: global | C12: root | D12: global.sim.fp_scale | E12: int | F12: ='Global Config'!D12 -> 1000 | G12: fp | H12: Global Config | I12: D12 | J12: TRUE | K12: TRUE | L12: ='Global Config'!K12 -> OK | M12: Масштаб fixed-point
A13: 8 | B13: global | C13: root | D13: global.sim.probability_min | E13: fp | F13: ='Global Config'!D13 -> 0 | G13: fp | H13: Global Config | I13: D13 | J13: TRUE | K13: TRUE | L13: ='Global Config'!K13 -> OK | M13: Минимум вероятности
A14: 9 | B14: global | C14: root | D14: global.sim.probability_max | E14: fp | F14: ='Global Config'!D14 -> 1000 | G14: fp | H14: Global Config | I14: D14 | J14: TRUE | K14: TRUE | L14: ='Global Config'!K14 -> OK | M14: Максимум вероятности
A15: 10 | B15: global | C15: root | D15: global.sim.multiplier_min | E15: fp | F15: ='Global Config'!D15 -> 250 | G15: fp | H15: Global Config | I15: D15 | J15: TRUE | K15: TRUE | L15: ='Global Config'!K15 -> OK | M15: Минимальный множитель веса
A16: 11 | B16: global | C16: root | D16: global.sim.multiplier_max | E16: fp | F16: ='Global Config'!D16 -> 3000 | G16: fp | H16: Global Config | I16: D16 | J16: TRUE | K16: TRUE | L16: ='Global Config'!K16 -> OK | M16: Максимальный множитель веса
A17: 12 | B17: global | C17: root | D17: global.sim.decision_weight_max | E17: int | F17: ='Global Config'!D17 -> 100000000 | G17: weight | H17: Global Config | I17: D17 | J17: TRUE | K17: TRUE | L17: ='Global Config'!K17 -> OK | M17: Максимальный итоговый вес
... A89: 84 | B89: global | C89: root | D89: fighter.gorilla.grip_tier_3 | E89: int | F89: ='Global Config'!D89 -> 800 | G89: resource | H89: Global Config | I89: D89 | J89: TRUE | K89: TRUE | L89: ='Global Config'!K89 -> OK | M89: Порог Grip III
A90: 85 | B90: fighter | C90: bear | D90: animal_id | E90: string | F90: ='Fighter Stats'!A6 -> bear | H90: Fighter Stats | I90: A6 | J90: TRUE | K90: TRUE | L90: ='Fighter Stats'!AA6 -> OK | M90: Источник Fighter Stats.Animal ID
A91: 86 | B91: fighter | C91: bear | D91: resource_id | E91: string | F91: ='Fighter Stats'!C6 -> rage | H91: Fighter Stats | I91: C6 | J91: TRUE | K91: TRUE | L91: ='Fighter Stats'!AA6 -> OK | M91: Источник Fighter Stats.Resource ID
A92: 87 | B92: fighter | C92: bear | D92: max_health | E92: int | F92: ='Fighter Stats'!D6 -> 1650 | H92: Fighter Stats | I92: D6 | J92: TRUE | K92: TRUE | L92: ='Fighter Stats'!AA6 -> OK | M92: Источник Fighter Stats.Max Health
A93: 88 | B93: fighter | C93: bear | D93: power | E93: int | F93: ='Fighter Stats'!E6 -> 130 | H93: Fighter Stats | I93: E6 | J93: TRUE | K93: TRUE | L93: ='Fighter Stats'!AA6 -> OK | M93: Источник Fighter Stats.Power
A94: 89 | B94: fighter | C94: bear | D94: armor | E94: int | F94: ='Fighter Stats'!F6 -> 75 | H94: Fighter Stats | I94: F6 | J94: TRUE | K94: TRUE | L94: ='Fighter Stats'!AA6 -> OK | M94: Источник Fighter Stats.Armor
A95: 90 | B95: fighter | C95: bear | D95: precision | E95: int | F95: ='Fighter Stats'!G6 -> 95 | H95: Fighter Stats | I95: G6 | J95: TRUE | K95: TRUE | L95: ='Fighter Stats'!AA6 -> OK | M95: Источник Fighter Stats.Precision
A96: 91 | B96: fighter | C96: bear | D96: evasion | E96: int | F96: ='Fighter Stats'!H6 -> 55 | H96: Fighter Stats | I96: H6 | J96: TRUE | K96: TRUE | L96: ='Fighter Stats'!AA6 -> OK | M96: Источник Fighter Stats.Evasion
A97: 92 | B97: fighter | C97: bear | D97: guard | E97: int | F97: ='Fighter Stats'!I6 -> 105 | H97: Fighter Stats | I97: I6 | J97: TRUE | K97: TRUE | L97: ='Fighter Stats'!AA6 -> OK | M97: Источник Fighter Stats.Guard
A98: 93 | B98: fighter | C98: bear | D98: guard_break | E98: int | F98: ='Fighter Stats'!J6 -> 120 | H98: Fighter Stats | I98: J6 | J98: TRUE | K98: TRUE | L98: ='Fighter Stats'!AA6 -> OK | M98: Источник Fighter Stats.Guard Break
A99: 94 | B99: fighter | C99: bear | D99: move_speed | E99: int | F99: ='Fighter Stats'!K6 -> 70 | H99: Fighter Stats | I99: K6 | J99: TRUE | K99: TRUE | L99: ='Fighter Stats'!AA6 -> OK | M99: Источник Fighter Stats.Move Speed
A100: 95 | B100: fighter | C100: bear | D100: action_speed | E100: int | F100: ='Fighter Stats'!L6 -> 85 | H100: Fighter Stats | I100: L6 | J100: TRUE | K100: TRUE | L100: ='Fighter Stats'!AA6 -> OK | M100: Источник Fighter Stats.Action Speed
A101: 96 | B101: fighter | C101: bear | D101: initiative | E101: int | F101: ='Fighter Stats'!M6 -> 85 | H101: Fighter Stats | I101: M6 | J101: TRUE | K101: TRUE | L101: ='Fighter Stats'!AA6 -> OK | M101: Источник Fighter Stats.Initiative
A102: 97 | B102: fighter | C102: bear | D102: control_power | E102: int | F102: ='Fighter Stats'!N6 -> 125 | H102: Fighter Stats | I102: N6 | J102: TRUE | K102: TRUE | L102: ='Fighter Stats'!AA6 -> OK | M102: Источник Fighter Stats.Control Power
A103: 98 | B103: fighter | C103: bear | D103: control_resistance | E103: int | F103: ='Fighter Stats'!O6 -> 125 | H103: Fighter Stats | I103: O6 | J103: TRUE | K103: TRUE | L103: ='Fighter Stats'!AA6 -> OK | M103: Источник Fighter Stats.Control Resistance
A104: 99 | B104: fighter | C104: bear | D104: mass | E104: int | F104: ='Fighter Stats'!P6 -> 130 | H104: Fighter Stats | I104: P6 | J104: TRUE | K104: TRUE | L104: ='Fighter Stats'!AA6 -> OK | M104: Источник Fighter Stats.Mass
A105: 100 | B105: fighter | C105: bear | D105: max_energy | E105: int | F105: ='Fighter Stats'!Q6 -> 1000 | H105: Fighter Stats | I105: Q6 | J105: TRUE | K105: TRUE | L105: ='Fighter Stats'!AA6 -> OK | M105: Источник Fighter Stats.Max Energy
A106: 101 | B106: fighter | C106: bear | D106: energy_regen | E106: int | F106: ='Fighter Stats'!R6 -> 12 | H106: Fighter Stats | I106: R6 | J106: TRUE | K106: TRUE | L106: ='Fighter Stats'!AA6 -> OK | M106: Источник Fighter Stats.Energy Regen / tick
A107: 102 | B107: fighter | C107: bear | D107: collision_radius | E107: int | F107: ='Fighter Stats'!S6 -> 520 | H107: Fighter Stats | I107: S6 | J107: TRUE | K107: TRUE | L107: ='Fighter Stats'!AA6 -> OK | M107: Источник Fighter Stats.Collision Radius
A108: 103 | B108: fighter | C108: bear | D108: start_resource | E108: int | F108: ='Fighter Stats'!T6 -> 0 | H108: Fighter Stats | I108: T6 | J108: TRUE | K108: TRUE | L108: ='Fighter Stats'!AA6 -> OK | M108: Источник Fighter Stats.Start Resource
A109: 104 | B109: fighter | C109: bear | D109: max_resource | E109: int | F109: ='Fighter Stats'!U6 -> 1000 | H109: Fighter Stats | I109: U6 | J109: TRUE | K109: TRUE | L109: ='Fighter Stats'!AA6 -> OK | M109: Источник Fighter Stats.Max Resource
A110: 105 | B110: fighter | C110: bear | D110: stagger_threshold | E110: int | F110: ='Fighter Stats'!V6 -> 260 | H110: Fighter Stats | I110: V6 | J110: TRUE | K110: TRUE | L110: ='Fighter Stats'!AA6 -> OK | M110: Источник Fighter Stats.Stagger Threshold
A111: 106 | B111: fighter | C111: kangaroo | D111: animal_id | E111: string | F111: ='Fighter Stats'!A7 -> kangaroo | H111: Fighter Stats | I111: A7 | J111: TRUE | K111: TRUE | L111: ='Fighter Stats'!AA7 -> OK | M111: Источник Fighter Stats.Animal ID
A112: 107 | B112: fighter | C112: kangaroo | D112: resource_id | E112: string | F112: ='Fighter Stats'!C7 -> tempo | H112: Fighter Stats | I112: C7 | J112: TRUE | K112: TRUE | L112: ='Fighter Stats'!AA7 -> OK | M112: Источник Fighter Stats.Resource ID
A113: 108 | B113: fighter | C113: kangaroo | D113: max_health | E113: int | F113: ='Fighter Stats'!D7 -> 1150 | H113: Fighter Stats | I113: D7 | J113: TRUE | K113: TRUE | L113: ='Fighter Stats'!AA7 -> OK | M113: Источник Fighter Stats.Max Health
A114: 109 | B114: fighter | C114: kangaroo | D114: power | E114: int | F114: ='Fighter Stats'!E7 -> 100 | H114: Fighter Stats | I114: E7 | J114: TRUE | K114: TRUE | L114: ='Fighter Stats'!AA7 -> OK | M114: Источник Fighter Stats.Power
A115: 110 | B115: fighter | C115: kangaroo | D115: armor | E115: int | F115: ='Fighter Stats'!F7 -> 40 | H115: Fighter Stats | I115: F7 | J115: TRUE | K115: TRUE | L115: ='Fighter Stats'!AA7 -> OK | M115: Источник Fighter Stats.Armor
A116: 111 | B116: fighter | C116: kangaroo | D116: precision | E116: int | F116: ='Fighter Stats'!G7 -> 125 | H116: Fighter Stats | I116: G7 | J116: TRUE | K116: TRUE | L116: ='Fighter Stats'!AA7 -> OK | M116: Источник Fighter Stats.Precision
A117: 112 | B117: fighter | C117: kangaroo | D117: evasion | E117: int | F117: ='Fighter Stats'!H7 -> 135 | H117: Fighter Stats | I117: H7 | J117: TRUE | K117: TRUE | L117: ='Fighter Stats'!AA7 -> OK | M117: Источник Fighter Stats.Evasion
A118: 113 | B118: fighter | C118: kangaroo | D118: guard | E118: int | F118: ='Fighter Stats'!I7 -> 65 | H118: Fighter Stats | I118: I7 | J118: TRUE | K118: TRUE | L118: ='Fighter Stats'!AA7 -> OK | M118: Источник Fighter Stats.Guard
A119: 114 | B119: fighter | C119: kangaroo | D119: guard_break | E119: int | F119: ='Fighter Stats'!J7 -> 80 | H119: Fighter Stats | I119: J7 | J119: TRUE | K119: TRUE | L119: ='Fighter Stats'!AA7 -> OK | M119: Источник Fighter Stats.Guard Break
A120: 115 | B120: fighter | C120: kangaroo | D120: move_speed | E120: int | F120: ='Fighter Stats'!K7 -> 135 | H120: Fighter Stats | I120: K7 | J120: TRUE | K120: TRUE | L120: ='Fighter Stats'!AA7 -> OK | M120: Источник Fighter Stats.Move Speed
A121: 116 | B121: fighter | C121: kangaroo | D121: action_speed | E121: int | F121: ='Fighter Stats'!L7 -> 125 | H121: Fighter Stats | I121: L7 | J121: TRUE | K121: TRUE | L121: ='Fighter Stats'!AA7 -> OK | M121: Источник Fighter Stats.Action Speed
A122: 117 | B122: fighter | C122: kangaroo | D122: initiative | E122: int | F122: ='Fighter Stats'!M7 -> 130 | H122: Fighter Stats | I122: M7 | J122: TRUE | K122: TRUE | L122: ='Fighter Stats'!AA7 -> OK | M122: Источник Fighter Stats.Initiative
A123: 118 | B123: fighter | C123: kangaroo | D123: control_power | E123: int | F123: ='Fighter Stats'!N7 -> 75 | H123: Fighter Stats | I123: N7 | J123: TRUE | K123: TRUE | L123: ='Fighter Stats'!AA7 -> OK | M123: Источник Fighter Stats.Control Power
A124: 119 | B124: fighter | C124: kangaroo | D124: control_resistance | E124: int | F124: ='Fighter Stats'!O7 -> 70 | H124: Fighter Stats | I124: O7 | J124: TRUE | K124: TRUE | L124: ='Fighter Stats'!AA7 -> OK | M124: Источник Fighter Stats.Control Resistance
A125: 120 | B125: fighter | C125: kangaroo | D125: mass | E125: int | F125: ='Fighter Stats'!P7 -> 70 | H125: Fighter Stats | I125: P7 | J125: TRUE | K125: TRUE | L125: ='Fighter Stats'!AA7 -> OK | M125: Источник Fighter Stats.Mass
A126: 121 | B126: fighter | C126: kangaroo | D126: max_energy | E126: int | F126: ='Fighter Stats'!Q7 -> 1000 | H126: Fighter Stats | I126: Q7 | J126: TRUE | K126: TRUE | L126: ='Fighter Stats'!AA7 -> OK | M126: Источник Fighter Stats.Max Energy
A127: 122 | B127: fighter | C127: kangaroo | D127: energy_regen | E127: int | F127: ='Fighter Stats'!R7 -> 15 | H127: Fighter Stats | I127: R7 | J127: TRUE | K127: TRUE | L127: ='Fighter Stats'!AA7 -> OK | M127: Источник Fighter Stats.Energy Regen / tick
A128: 123 | B128: fighter | C128: kangaroo | D128: collision_radius | E128: int | F128: ='Fighter Stats'!S7 -> 430 | H128: Fighter Stats | I128: S7 | J128: TRUE | K128: TRUE | L128: ='Fighter Stats'!AA7 -> OK | M128: Источник Fighter Stats.Collision Radius
A129: 124 | B129: fighter | C129: kangaroo | D129: start_resource | E129: int | F129: ='Fighter Stats'!T7 -> 0 | H129: Fighter Stats | I129: T7 | J129: TRUE | K129: TRUE | L129: ='Fighter Stats'!AA7 -> OK | M129: Источник Fighter Stats.Start Resource
A130: 125 | B130: fighter | C130: kangaroo | D130: max_resource | E130: int | F130: ='Fighter Stats'!U7 -> 1000 | H130: Fighter Stats | I130: U7 | J130: TRUE | K130: TRUE | L130: ='Fighter Stats'!AA7 -> OK | M130: Источник Fighter Stats.Max Resource
A131: 126 | B131: fighter | C131: kangaroo | D131: stagger_threshold | E131: int | F131: ='Fighter Stats'!V7 -> 180 | H131: Fighter Stats | I131: V7 | J131: TRUE | K131: TRUE | L131: ='Fighter Stats'!AA7 -> OK | M131: Источник Fighter Stats.Stagger Threshold
A132: 127 | B132: fighter | C132: gorilla | D132: animal_id | E132: string | F132: ='Fighter Stats'!A8 -> gorilla | H132: Fighter Stats | I132: A8 | J132: TRUE | K132: TRUE | L132: ='Fighter Stats'!AA8 -> OK | M132: Источник Fighter Stats.Animal ID
A133: 128 | B133: fighter | C133: gorilla | D133: resource_id | E133: string | F133: ='Fighter Stats'!C8 -> grip | H133: Fighter Stats | I133: C8 | J133: TRUE | K133: TRUE | L133: ='Fighter Stats'!AA8 -> OK | M133: Источник Fighter Stats.Resource ID
A134: 129 | B134: fighter | C134: gorilla | D134: max_health | E134: int | F134: ='Fighter Stats'!D8 -> 1450 | H134: Fighter Stats | I134: D8 | J134: TRUE | K134: TRUE | L134: ='Fighter Stats'!AA8 -> OK | M134: Источник Fighter Stats.Max Health
A135: 130 | B135: fighter | C135: gorilla | D135: power | E135: int | F135: ='Fighter Stats'!E8 -> 110 | H135: Fighter Stats | I135: E8 | J135: TRUE | K135: TRUE | L135: ='Fighter Stats'!AA8 -> OK | M135: Источник Fighter Stats.Power
A136: 131 | B136: fighter | C136: gorilla | D136: armor | E136: int | F136: ='Fighter Stats'!F8 -> 95 | H136: Fighter Stats | I136: F8 | J136: TRUE | K136: TRUE | L136: ='Fighter Stats'!AA8 -> OK | M136: Источник Fighter Stats.Armor
A137: 132 | B137: fighter | C137: gorilla | D137: precision | E137: int | F137: ='Fighter Stats'!G8 -> 90 | H137: Fighter Stats | I137: G8 | J137: TRUE | K137: TRUE | L137: ='Fighter Stats'!AA8 -> OK | M137: Источник Fighter Stats.Precision
A138: 133 | B138: fighter | C138: gorilla | D138: evasion | E138: int | F138: ='Fighter Stats'!H8 -> 45 | H138: Fighter Stats | I138: H8 | J138: TRUE | K138: TRUE | L138: ='Fighter Stats'!AA8 -> OK | M138: Источник Fighter Stats.Evasion
A139: 134 | B139: fighter | C139: gorilla | D139: guard | E139: int | F139: ='Fighter Stats'!I8 -> 140 | H139: Fighter Stats | I139: I8 | J139: TRUE | K139: TRUE | L139: ='Fighter Stats'!AA8 -> OK | M139: Источник Fighter Stats.Guard
A140: 135 | B140: fighter | C140: gorilla | D140: guard_break | E140: int | F140: ='Fighter Stats'!J8 -> 105 | H140: Fighter Stats | I140: J8 | J140: TRUE | K140: TRUE | L140: ='Fighter Stats'!AA8 -> OK | M140: Источник Fighter Stats.Guard Break
A141: 136 | B141: fighter | C141: gorilla | D141: move_speed | E141: int | F141: ='Fighter Stats'!K8 -> 75 | H141: Fighter Stats | I141: K8 | J141: TRUE | K141: TRUE | L141: ='Fighter Stats'!AA8 -> OK | M141: Источник Fighter Stats.Move Speed
A142: 137 | B142: fighter | C142: gorilla | D142: action_speed | E142: int | F142: ='Fighter Stats'!L8 -> 105 | H142: Fighter Stats | I142: L8 | J142: TRUE | K142: TRUE | L142: ='Fighter Stats'!AA8 -> OK | M142: Источник Fighter Stats.Action Speed
A143: 138 | B143: fighter | C143: gorilla | D143: initiative | E143: int | F143: ='Fighter Stats'!M8 -> 95 | H143: Fighter Stats | I143: M8 | J143: TRUE | K143: TRUE | L143: ='Fighter Stats'!AA8 -> OK | M143: Источник Fighter Stats.Initiative
A144: 139 | B144: fighter | C144: gorilla | D144: control_power | E144: int | F144: ='Fighter Stats'!N8 -> 145 | H144: Fighter Stats | I144: N8 | J144: TRUE | K144: TRUE | L144: ='Fighter Stats'!AA8 -> OK | M144: Источник Fighter Stats.Control Power
A145: 140 | B145: fighter | C145: gorilla | D145: control_resistance | E145: int | F145: ='Fighter Stats'!O8 -> 130 | H145: Fighter Stats | I145: O8 | J145: TRUE | K145: TRUE | L145: ='Fighter Stats'!AA8 -> OK | M145: Источник Fighter Stats.Control Resistance
A146: 141 | B146: fighter | C146: gorilla | D146: mass | E146: int | F146: ='Fighter Stats'!P8 -> 150 | H146: Fighter Stats | I146: P8 | J146: TRUE | K146: TRUE | L146: ='Fighter Stats'!AA8 -> OK | M146: Источник Fighter Stats.Mass
A147: 142 | B147: fighter | C147: gorilla | D147: max_energy | E147: int | F147: ='Fighter Stats'!Q8 -> 1000 | H147: Fighter Stats | I147: Q8 | J147: TRUE | K147: TRUE | L147: ='Fighter Stats'!AA8 -> OK | M147: Источник Fighter Stats.Max Energy
A148: 143 | B148: fighter | C148: gorilla | D148: energy_regen | E148: int | F148: ='Fighter Stats'!R8 -> 11 | H148: Fighter Stats | I148: R8 | J148: TRUE | K148: TRUE | L148: ='Fighter Stats'!AA8 -> OK | M148: Источник Fighter Stats.Energy Regen / tick
A149: 144 | B149: fighter | C149: gorilla | D149: collision_radius | E149: int | F149: ='Fighter Stats'!S8 -> 550 | H149: Fighter Stats | I149: S8 | J149: TRUE | K149: TRUE | L149: ='Fighter Stats'!AA8 -> OK | M149: Источник Fighter Stats.Collision Radius
A150: 145 | B150: fighter | C150: gorilla | D150: start_resource | E150: int | F150: ='Fighter Stats'!T8 -> 0 | H150: Fighter Stats | I150: T8 | J150: TRUE | K150: TRUE | L150: ='Fighter Stats'!AA8 -> OK | M150: Источник Fighter Stats.Start Resource
A151: 146 | B151: fighter | C151: gorilla | D151: max_resource | E151: int | F151: ='Fighter Stats'!U8 -> 1000 | H151: Fighter Stats | I151: U8 | J151: TRUE | K151: TRUE | L151: ='Fighter Stats'!AA8 -> OK | M151: Источник Fighter Stats.Max Resource
A152: 147 | B152: fighter | C152: gorilla | D152: stagger_threshold | E152: int | F152: ='Fighter Stats'!V8 -> 300 | H152: Fighter Stats | I152: V8 | J152: TRUE | K152: TRUE | L152: ='Fighter Stats'!AA8 -> OK | M152: Источник Fighter Stats.Stagger Threshold
A153: 148 | B153: action | C153: sys_approach | D153: action_id | E153: string | F153: =Actions!A6 -> sys_approach | H153: Actions | I153: A6 | J153: TRUE | K153: TRUE | L153: =Actions!BE6 -> OK | M153: Источник Actions.Action ID
A154: 149 | B154: action | C154: sys_approach | D154: animal_id | E154: string | F154: =Actions!B6 -> all | H154: Actions | I154: B6 | J154: TRUE | K154: TRUE | L154: =Actions!BE6 -> OK | M154: Источник Actions.Animal ID
A155: 150 | B155: action | C155: sys_approach | D155: slot_type | E155: string | F155: =Actions!D6 -> System | H155: Actions | I155: D6 | J155: TRUE | K155: TRUE | L155: =Actions!BE6 -> OK | M155: Источник Actions.Slot Type
A156: 151 | B156: action | C156: sys_approach | D156: category | E156: string | F156: =Actions!E6 -> Movement | H156: Actions | I156: E6 | J156: TRUE | K156: TRUE | L156: =Actions!BE6 -> OK | M156: Источник Actions.Category
A157: 152 | B157: action | C157: sys_approach | D157: tags | E157: string | F157: =Actions!F6 -> system|movement|approach | H157: Actions | I157: F6 | J157: TRUE | K157: TRUE | L157: =Actions!BE6 -> OK | M157: Источник Actions.Tags
A158: 153 | B158: action | C158: sys_approach | D158: base_weight | E158: int | F158: =Actions!G6 -> 650 | H158: Actions | I158: G6 | J158: TRUE | K158: TRUE | L158: =Actions!BE6 -> OK | M158: Источник Actions.Base Weight
A159: 154 | B159: action | C159: sys_approach | D159: preferred_range_min | E159: int | F159: =Actions!H6 -> 0 | H159: Actions | I159: H6 | J159: TRUE | K159: TRUE | L159: =Actions!BE6 -> OK | M159: Источник Actions.Preferred Range Min
A160: 155 | B160: action | C160: sys_approach | D160: preferred_range_max | E160: int | F160: =Actions!I6 -> 1500 | H160: Actions | I160: I6 | J160: TRUE | K160: TRUE | L160: =Actions!BE6 -> OK | M160: Источник Actions.Preferred Range Max
A161: 156 | B161: action | C161: sys_approach | D161: hit_range_min | E161: int | F161: =Actions!J6 -> 0 | H161: Actions | I161: J6 | J161: TRUE | K161: TRUE | L161: =Actions!BE6 -> OK | M161: Источник Actions.Hit Range Min
A162: 157 | B162: action | C162: sys_approach | D162: hit_range_max | E162: int | F162: =Actions!K6 -> 0 | H162: Actions | I162: K6 | J162: TRUE | K162: TRUE | L162: =Actions!BE6 -> OK | M162: Источник Actions.Hit Range Max
A163: 158 | B163: action | C163: sys_approach | D163: energy_cost | E163: int | F163: =Actions!L6 -> 0 | H163: Actions | I163: L6 | J163: TRUE | K163: TRUE | L163: =Actions!BE6 -> OK | M163: Источник Actions.Energy Cost
A164: 159 | B164: action | C164: sys_approach | D164: resource_cost | E164: int | F164: =Actions!M6 -> 0 | H164: Actions | I164: M6 | J164: TRUE | K164: TRUE | L164: =Actions!BE6 -> OK | M164: Источник Actions.Resource Cost
A165: 160 | B165: action | C165: sys_approach | D165: base_damage | E165: int | F165: =Actions!N6 -> 0 | H165: Actions | I165: N6 | J165: TRUE | K165: TRUE | L165: =Actions!BE6 -> OK | M165: Источник Actions.Base Damage / hit
A166: 161 | B166: action | C166: sys_approach | D166: power_ratio_fp | E166: int | F166: =Actions!O6 -> 0 | H166: Actions | I166: O6 | J166: TRUE | K166: TRUE | L166: =Actions!BE6 -> OK | M166: Источник Actions.Power Ratio FP
A167: 162 | B167: action | C167: sys_approach | D167: min_damage | E167: int | F167: =Actions!P6 -> 0 | H167: Actions | I167: P6 | J167: TRUE | K167: TRUE | L167: =Actions!BE6 -> OK | M167: Источник Actions.Min Damage
A168: 163 | B168: action | C168: sys_approach | D168: chip_min | E168: int | F168: =Actions!Q6 -> 0 | H168: Actions | I168: Q6 | J168: TRUE | K168: TRUE | L168: =Actions!BE6 -> OK | M168: Источник Actions.Chip Min
A169: 164 | B169: action | C169: sys_approach | D169: startup_base_ticks | E169: int | F169: =Actions!R6 -> 1 | H169: Actions | I169: R6 | J169: TRUE | K169: TRUE | L169: =Actions!BE6 -> OK | M169: Источник Actions.Startup Base Ticks
A170: 165 | B170: action | C170: sys_approach | D170: startup_min_ticks | E170: int | F170: =Actions!S6 -> 1 | H170: Actions | I170: S6 | J170: TRUE | K170: TRUE | L170: =Actions!BE6 -> OK | M170: Источник Actions.Startup Min Ticks
A171: 166 | B171: action | C171: sys_approach | D171: startup_max_ticks | E171: int | F171: =Actions!T6 -> 1 | H171: Actions | I171: T6 | J171: TRUE | K171: TRUE | L171: =Actions!BE6 -> OK | M171: Источник Actions.Startup Max Ticks
A172: 167 | B172: action | C172: sys_approach | D172: active_ticks | E172: int | F172: =Actions!U6 -> 5 | H172: Actions | I172: U6 | J172: TRUE | K172: TRUE | L172: =Actions!BE6 -> OK | M172: Источник Actions.Active Ticks
...

Sheet Validation
A1: Validation
A2: Единый список автоматических проверок перед JSON-экспортом
A3: Экспорт запрещён при любом Result=ERROR. Сначала исправьте исходный лист; Validation и JSON Map обновятся автоматически.
A5: Check ID | B5: Source Sheet | C5: Entity ID | D5: Rule | E5: Result | F5: Severity | G5: Details
A6: CHK-0001 | B6: Global Config | C6: global.sim.schema_version | D6: Обязательные поля и диапазоны | E6: ='Global Config'!K6 -> OK | F6: Error | G6: ='Global Config'!A6 -> global.sim.schema_version
A7: CHK-0002 | B7: Global Config | C7: global.sim.config_version | D7: Обязательные поля и диапазоны | E7: ='Global Config'!K7 -> OK | F7: Error | G7: ='Global Config'!A7 -> global.sim.config_version
A8: CHK-0003 | B8: Global Config | C8: global.sim.rng_version | D8: Обязательные поля и диапазоны | E8: ='Global Config'!K8 -> OK | F8: Error | G8: ='Global Config'!A8 -> global.sim.rng_version
A9: CHK-0004 | B9: Global Config | C9: global.sim.ordering_version | D9: Обязательные поля и диапазоны | E9: ='Global Config'!K9 -> OK | F9: Error | G9: ='Global Config'!A9 -> global.sim.ordering_version
A10: CHK-0005 | B10: Global Config | C10: global.sim.tick_ms | D10: Обязательные поля и диапазоны | E10: ='Global Config'!K10 -> OK | F10: Error | G10: ='Global Config'!A10 -> global.sim.tick_ms
A11: CHK-0006 | B11: Global Config | C11: battle.time_limit_ticks | D11: Обязательные поля и диапазоны | E11: ='Global Config'!K11 -> OK | F11: Error | G11: ='Global Config'!A11 -> battle.time_limit_ticks
A12: CHK-0007 | B12: Global Config | C12: global.sim.fp_scale | D12: Обязательные поля и диапазоны | E12: ='Global Config'!K12 -> OK | F12: Error | G12: ='Global Config'!A12 -> global.sim.fp_scale
A13: CHK-0008 | B13: Global Config | C13: global.sim.probability_min | D13: Обязательные поля и диапазоны | E13: ='Global Config'!K13 -> OK | F13: Error | G13: ='Global Config'!A13 -> global.sim.probability_min
A14: CHK-0009 | B14: Global Config | C14: global.sim.probability_max | D14: Обязательные поля и диапазоны | E14: ='Global Config'!K14 -> OK | F14: Error | G14: ='Global Config'!A14 -> global.sim.probability_max
A15: CHK-0010 | B15: Global Config | C15: global.sim.multiplier_min | D15: Обязательные поля и диапазоны | E15: ='Global Config'!K15 -> OK | F15: Error | G15: ='Global Config'!A15 -> global.sim.multiplier_min
A16: CHK-0011 | B16: Global Config | C16: global.sim.multiplier_max | D16: Обязательные поля и диапазоны | E16: ='Global Config'!K16 -> OK | F16: Error | G16: ='Global Config'!A16 -> global.sim.multiplier_max
A17: CHK-0012 | B17: Global Config | C17: global.sim.decision_weight_max | D17: Обязательные поля и диапазоны | E17: ='Global Config'!K17 -> OK | F17: Error | G17: ='Global Config'!A17 -> global.sim.decision_weight_max
... A89: CHK-0084 | B89: Global Config | C89: fighter.gorilla.grip_tier_3 | D89: Обязательные поля и диапазоны | E89: ='Global Config'!K89 -> OK | F89: Error | G89: ='Global Config'!A89 -> fighter.gorilla.grip_tier_3
A90: CHK-0085 | B90: Fighter Stats | C90: bear | D90: Обязательные поля и диапазоны | E90: ='Fighter Stats'!AA6 -> OK | F90: Error | G90: ='Fighter Stats'!A6 -> bear
A91: CHK-0086 | B91: Fighter Stats | C91: kangaroo | D91: Обязательные поля и диапазоны | E91: ='Fighter Stats'!AA7 -> OK | F91: Error | G91: ='Fighter Stats'!A7 -> kangaroo
A92: CHK-0087 | B92: Fighter Stats | C92: gorilla | D92: Обязательные поля и диапазоны | E92: ='Fighter Stats'!AA8 -> OK | F92: Error | G92: ='Fighter Stats'!A8 -> gorilla
A93: CHK-0088 | B93: Actions | C93: sys_approach | D93: Обязательные поля и диапазоны | E93: =Actions!BE6 -> OK | F93: Error | G93: =Actions!A6 -> sys_approach
A94: CHK-0089 | B94: Actions | C94: sys_retreat | D94: Обязательные поля и диапазоны | E94: =Actions!BE7 -> OK | F94: Error | G94: =Actions!A7 -> sys_retreat
A95: CHK-0090 | B95: Actions | C95: sys_wait | D95: Обязательные поля и диапазоны | E95: =Actions!BE8 -> OK | F95: Error | G95: =Actions!A8 -> sys_wait
A96: CHK-0091 | B96: Actions | C96: bear_paw_jab | D96: Обязательные поля и диапазоны | E96: =Actions!BE9 -> OK | F96: Error | G96: =Actions!A9 -> bear_paw_jab
A97: CHK-0092 | B97: Actions | C97: bear_crushing_swipe | D97: Обязательные поля и диапазоны | E97: =Actions!BE10 -> OK | F97: Error | G97: =Actions!A10 -> bear_crushing_swipe
A98: CHK-0093 | B98: Actions | C98: bear_guarded_advance | D98: Обязательные поля и диапазоны | E98: =Actions!BE11 -> OK | F98: Error | G98: =Actions!A11 -> bear_guarded_advance
A99: CHK-0094 | B99: Actions | C99: bear_body_check | D99: Обязательные поля и диапазоны | E99: =Actions!BE12 -> OK | F99: Error | G99: =Actions!A12 -> bear_body_check
A100: CHK-0095 | B100: Actions | C100: bear_rampage_charge | D100: Обязательные поля и диапазоны | E100: =Actions!BE13 -> OK | F100: Error | G100: =Actions!A13 -> bear_rampage_charge
A101: CHK-0096 | B101: Actions | C101: bear_earthbreaker | D101: Обязательные поля и диапазоны | E101: =Actions!BE14 -> OK | F101: Error | G101: =Actions!A14 -> bear_earthbreaker
A102: CHK-0097 | B102: Actions | C102: bear_fury_maul | D102: Обязательные поля и диапазоны | E102: =Actions!BE15 -> OK | F102: Error | G102: =Actions!A15 -> bear_fury_maul
A103: CHK-0098 | B103: Actions | C103: kangaroo_lead_jab | D103: Обязательные поля и диапазоны | E103: =Actions!BE16 -> OK | F103: Error | G103: =Actions!A16 -> kangaroo_lead_jab
A104: CHK-0099 | B104: Actions | C104: kangaroo_push_kick | D104: Обязательные поля и диапазоны | E104: =Actions!BE17 -> OK | F104: Error | G104: =Actions!A17 -> kangaroo_push_kick
... A116: CHK-0111 | B116: Actions | C116: gorilla_wall_breaker | D116: Обязательные поля и диапазоны | E116: =Actions!BE29 -> OK | F116: Error | G116: =Actions!A29 -> gorilla_wall_breaker
A117: CHK-0112 | B117: Passives | C117: bear_thick_hide | D117: Обязательные поля и диапазоны | E117: =Passives!V6 -> OK | F117: Error | G117: =Passives!A6 -> bear_thick_hide
A118: CHK-0113 | B118: Passives | C118: bear_pressure_fuels_rage | D118: Обязательные поля и диапазоны | E118: =Passives!V7 -> OK | F118: Error | G118: =Passives!A7 -> bear_pressure_fuels_rage
A119: CHK-0114 | B119: Passives | C119: kangaroo_never_still | D119: Обязательные поля и диапазоны | E119: =Passives!V8 -> OK | F119: Error | G119: =Passives!A8 -> kangaroo_never_still
A120: CHK-0115 | B120: Passives | C120: kangaroo_clean_rhythm | D120: Обязательные поля и диапазоны | E120: =Passives!V9 -> OK | F120: Error | G120: =Passives!A9 -> kangaroo_clean_rhythm
A121: CHK-0116 | B121: Passives | C121: gorilla_territorial_pressure | D121: Обязательные поля и диапазоны | E121: =Passives!V10 -> OK | F121: Error | G121: =Passives!A10 -> gorilla_territorial_pressure
A122: CHK-0117 | B122: Passives | C122: gorilla_iron_grip | D122: Обязательные поля и диапазоны | E122: =Passives!V11 -> OK | F122: Error | G122: =Passives!A11 -> gorilla_iron_grip
A123: CHK-0118 | B123: Effects | C123: effect_bear_thick_hide | D123: Обязательные поля и диапазоны | E123: =Effects!U6 -> OK | F123: Error | G123: =Effects!A6 -> effect_bear_thick_hide
A124: CHK-0119 | B124: Effects | C124: effect_kangaroo_clean_rhythm | D124: Обязательные поля и диапазоны | E124: =Effects!U7 -> OK | F124: Error | G124: =Effects!A7 -> effect_kangaroo_clean_rhythm
A125: CHK-0120 | B125: Effects | C125: effect_gorilla_wall_pressure | D125: Обязательные поля и диапазоны | E125: =Effects!U8 -> OK | F125: Error | G125: =Effects!A8 -> effect_gorilla_wall_pressure
A126: CHK-0121 | B126: Effects | C126: effect_gorilla_iron_grip | D126: Обязательные поля и диапазоны | E126: =Effects!U9 -> OK | F126: Error | G126: =Effects!A9 -> effect_gorilla_iron_grip
A127: CHK-0122 | B127: Effects | C127: effect_guard_broken | D127: Обязательные поля и диапазоны | E127: =Effects!U10 -> OK | F127: Error | G127: =Effects!A10 -> effect_guard_broken
A128: CHK-0123 | B128: Effects | C128: effect_exposed | D128: Обязательные поля и диапазоны | E128: =Effects!U11 -> OK | F128: Error | G128: =Effects!A11 -> effect_exposed
A129: CHK-0124 | B129: Effects | C129: effect_control_fatigue | D129: Обязательные поля и диапазоны | E129: =Effects!U12 -> OK | F129: Error | G129: =Effects!A12 -> effect_control_fatigue
A130: CHK-0125 | B130: Effects | C130: effect_control_immunity | D130: Обязательные поля и диапазоны | E130: =Effects!U13 -> OK | F130: Error | G130: =Effects!A13 -> effect_control_immunity
A131: CHK-0126 | B131: Effects | C131: effect_grab_lockout | D131: Обязательные поля и диапазоны | E131: =Effects!U14 -> OK | F131: Error | G131: =Effects!A14 -> effect_grab_lockout
A132: CHK-0127 | B132: Effects | C132: effect_wakeup_immunity | D132: Обязательные поля и диапазоны | E132: =Effects!U15 -> OK | F132: Error | G132: =Effects!A15 -> effect_wakeup_immunity
A133: CHK-0128 | B133: Tactics | C133: tactic_pressure | D133: Обязательные поля и диапазоны | E133: =Tactics!V6 -> OK | F133: Error | G133: =Tactics!A6 -> tactic_pressure
A134: CHK-0129 | B134: Tactics | C134: tactic_counter | D134: Обязательные поля и диапазоны | E134: =Tactics!V7 -> OK | F134: Error | G134: =Tactics!A7 -> tactic_counter
A135: CHK-0130 | B135: Tactics | C135: tactic_position | D135: Обязательные поля и диапазоны | E135: =Tactics!V8 -> OK | F135: Error | G135: =Tactics!A8 -> tactic_position
A136: CHK-0131 | B136: Tactics | C136: tactic_signature | D136: Обязательные поля и диапазоны | E136: =Tactics!V9 -> OK | F136: Error | G136: =Tactics!A9 -> tactic_signature
A137: CHK-0132 | B137: Gear | C137: gear_offense_power_wraps | D137: Обязательные поля и диапазоны | E137: =Gear!M6 -> OK | F137: Error | G137: =Gear!A6 -> gear_offense_power_wraps
A138: CHK-0133 | B138: Gear | C138: gear_offense_precision_lens | D138: Обязательные поля и диапазоны | E138: =Gear!M7 -> OK | F138: Error | G138: =Gear!A7 -> gear_offense_precision_lens
A139: CHK-0134 | B139: Gear | C139: gear_offense_guardbreaker | D139: Обязательные поля и диапазоны | E139: =Gear!M8 -> OK | F139: Error | G139: =Gear!A8 -> gear_offense_guardbreaker
A140: CHK-0135 | B140: Gear | C140: gear_defense_vital_harness | D140: Обязательные поля и диапазоны | E140: =Gear!M9 -> OK | F140: Error | G140: =Gear!A9 -> gear_defense_vital_harness
A141: CHK-0136 | B141: Gear | C141: gear_defense_reinforced_hide | D141: Обязательные поля и диапазоны | E141: =Gear!M10 -> OK | F141: Error | G141: =Gear!A10 -> gear_defense_reinforced_hide
A142: CHK-0137 | B142: Gear | C142: gear_defense_control_brace | D142: Обязательные поля и диапазоны | E142: =Gear!M11 -> OK | F142: Error | G142: =Gear!A11 -> gear_defense_control_brace
A143: CHK-0138 | B143: Gear | C143: gear_utility_sprint_soles | D143: Обязательные поля и диапазоны | E143: =Gear!M12 -> OK | F143: Error | G143: =Gear!A12 -> gear_utility_sprint_soles
A144: CHK-0139 | B144: Gear | C144: gear_utility_quickening_cord | D144: Обязательные поля и диапазоны | E144: =Gear!M13 -> OK | F144: Error | G144: =Gear!A13 -> gear_utility_quickening_cord
A145: CHK-0140 | B145: Gear | C145: gear_utility_energy_cell | D145: Обязательные поля и диапазоны | E145: =Gear!M14 -> OK | F145: Error | G145: =Gear!A14 -> gear_utility_energy_cell
A146: CHK-0141 | B146: Test Builds | C146: build_bear_default | D146: Ссылочная целостность сборки | E146: ='Test Builds'!N6 -> OK | F146: Error | G146: ='Test Builds'!A6 -> build_bear_default
A147: CHK-0142 | B147: Test Builds | C147: build_bear_anti_kite | D147: Ссылочная целостность сборки | E147: ='Test Builds'!N7 -> OK | F147: Error | G147: ='Test Builds'!A7 -> build_bear_anti_kite
A148: CHK-0143 | B148: Test Builds | C148: build_bear_counter_heavy | D148: Ссылочная целостность сборки | E148: ='Test Builds'!N8 -> OK | F148: Error | G148: ='Test Builds'!A8 -> build_bear_counter_heavy
A149: CHK-0144 | B149: Test Builds | C149: build_bear_signature | D149: Ссылочная целостность сборки | E149: ='Test Builds'!N9 -> OK | F149: Error | G149: ='Test Builds'!A9 -> build_bear_signature
A150: CHK-0145 | B150: Test Builds | C150: build_kangaroo_default | D150: Ссылочная целостность сборки | E150: ='Test Builds'!N10 -> OK | F150: Error | G150: ='Test Builds'!A10 -> build_kangaroo_default
A151: CHK-0146 | B151: Test Builds | C151: build_kangaroo_anti_grab | D151: Ссылочная целостность сборки | E151: ='Test Builds'!N11 -> OK | F151: Error | G151: ='Test Builds'!A11 -> build_kangaroo_anti_grab
A152: CHK-0147 | B152: Test Builds | C152: build_kangaroo_kite | D152: Ссылочная целостность сборки | E152: ='Test Builds'!N12 -> OK | F152: Error | G152: ='Test Builds'!A12 -> build_kangaroo_kite
A153: CHK-0148 | B153: Test Builds | C153: build_kangaroo_signature | D153: Ссылочная целостность сборки | E153: ='Test Builds'!N13 -> OK | F153: Error | G153: ='Test Builds'!A13 -> build_kangaroo_signature
A154: CHK-0149 | B154: Test Builds | C154: build_gorilla_default | D154: Ссылочная целостность сборки | E154: ='Test Builds'!N14 -> OK | F154: Error | G154: ='Test Builds'!A14 -> build_gorilla_default
A155: CHK-0150 | B155: Test Builds | C155: build_gorilla_anti_heavy | D155: Ссылочная целостность сборки | E155: ='Test Builds'!N15 -> OK | F155: Error | G155: ='Test Builds'!A15 -> build_gorilla_anti_heavy
A156: CHK-0151 | B156: Test Builds | C156: build_gorilla_wall_pressure | D156: Ссылочная целостность сборки | E156: ='Test Builds'!N16 -> OK | F156: Error | G156: ='Test Builds'!A16 -> build_gorilla_wall_pressure
A157: CHK-0152 | B157: Test Builds | C157: build_gorilla_signature | D157: Ссылочная целостность сборки | E157: ='Test Builds'!N17 -> OK | F157: Error | G157: ='Test Builds'!A17 -> build_gorilla_signature
A158: CHK-0153 | B158: Expected Matchups | C158: bear_vs_bear | D158: Диапазоны и контрольные сборки | E158: ='Expected Matchups'!S6 -> OK | F158: Error | G158: ='Expected Matchups'!A6 -> bear_vs_bear
A159: CHK-0154 | B159: Expected Matchups | C159: bear_vs_kangaroo | D159: Диапазоны и контрольные сборки | E159: ='Expected Matchups'!S7 -> OK | F159: Error | G159: ='Expected Matchups'!A7 -> bear_vs_kangaroo
A160: CHK-0155 | B160: Expected Matchups | C160: bear_vs_gorilla | D160: Диапазоны и контрольные сборки | E160: ='Expected Matchups'!S8 -> OK | F160: Error | G160: ='Expected Matchups'!A8 -> bear_vs_gorilla
A161: CHK-0156 | B161: Expected Matchups | C161: kangaroo_vs_bear | D161: Диапазоны и контрольные сборки | E161: ='Expected Matchups'!S9 -> OK | F161: Error | G161: ='Expected Matchups'!A9 -> kangaroo_vs_bear
A162: CHK-0157 | B162: Expected Matchups | C162: kangaroo_vs_kangaroo | D162: Диапазоны и контрольные сборки | E162: ='Expected Matchups'!S10 -> OK | F162: Error | G162: ='Expected Matchups'!A10 -> kangaroo_vs_kangaroo
A163: CHK-0158 | B163: Expected Matchups | C163: kangaroo_vs_gorilla | D163: Диапазоны и контрольные сборки | E163: ='Expected Matchups'!S11 -> OK | F163: Error | G163: ='Expected Matchups'!A11 -> kangaroo_vs_gorilla
A164: CHK-0159 | B164: Expected Matchups | C164: gorilla_vs_bear | D164: Диапазоны и контрольные сборки | E164: ='Expected Matchups'!S12 -> OK | F164: Error | G164: ='Expected Matchups'!A12 -> gorilla_vs_bear
A165: CHK-0160 | B165: Expected Matchups | C165: gorilla_vs_kangaroo | D165: Диапазоны и контрольные сборки | E165: ='Expected Matchups'!S13 -> OK | F165: Error | G165: ='Expected Matchups'!A13 -> gorilla_vs_kangaroo
A166: CHK-0161 | B166: Expected Matchups | C166: gorilla_vs_gorilla | D166: Диапазоны и контрольные сборки | E166: ='Expected Matchups'!S14 -> OK | F166: Error | G166: ='Expected Matchups'!A14 -> gorilla_vs_gorilla

Sheet Effect Rules
A1: Effect Rules — combat.balance/0.2
A2: WP-10: явные bindings. Global/Self = semantic subject события.
A3: OPEN-WP10-08; CLOSED 2026-10-03. Полные passive/gear triggers — WP-11.
A5: Rule ID | B5: Owner Kind | C5: Owner ID | D5: Trigger | E5: Recipient | F5: Condition | G5: Primitive | H5: Effect ID | I5: Priority | J5: Internal Cooldown Ticks | K5: Max Activations / Tick | L5: Max Activations / Battle | M5: Once Per Event | N5: Status | O5: Notes RU | P5: Validation
A6: rule_control_fatigue | B6: Global | C6: global | D6: ControlEnded | E6: Self | F6: LivingTarget | G6: ApplyEffect | H6: effect_control_fatigue | I6: 0 | J6: 0 | K6: 1 | L6: 999 | M6: 1 | N6: FIXED | O6: OPEN-WP10-08/17..20; global Self is the hook subject. | P6: =IF(AND(A6<>"",C6<>"",H6<>"",J6>=0,K6>=1,L6>=1,M6=1),"OK","ERROR") -> OK
A7: rule_control_immunity | B7: Global | C7: global | D7: FatigueThresholdReached | E7: Self | F7: LivingTarget | G7: ApplyEffect | H7: effect_control_immunity | I7: 0 | J7: 0 | K7: 1 | L7: 999 | M7: 1 | N7: FIXED | O7: OPEN-WP10-08/17..20; global Self is the hook subject. | P7: =IF(AND(A7<>"",C7<>"",H7<>"",J7>=0,K7>=1,L7>=1,M7=1),"OK","ERROR") -> OK
A8: rule_grab_lockout | B8: Global | C8: global | D8: GrabEnded | E8: Self | F8: LivingTarget | G8: ApplyEffect | H8: effect_grab_lockout | I8: 0 | J8: 0 | K8: 1 | L8: 999 | M8: 1 | N8: FIXED | O8: OPEN-WP10-08/17..20; global Self is the hook subject. | P8: =IF(AND(A8<>"",C8<>"",H8<>"",J8>=0,K8>=1,L8>=1,M8=1),"OK","ERROR") -> OK
A9: rule_wakeup_immunity | B9: Global | C9: global | D9: WakeupCompleted | E9: Self | F9: LivingTarget | G9: ApplyEffect | H9: effect_wakeup_immunity | I9: 0 | J9: 0 | K9: 1 | L9: 999 | M9: 1 | N9: FIXED | O9: OPEN-WP10-08/17..20; global Self is the hook subject. | P9: =IF(AND(A9<>"",C9<>"",H9<>"",J9>=0,K9>=1,L9>=1,M9=1),"OK","ERROR") -> OK
A10: rule_guard_broken | B10: Global | C10: global | D10: GuardBreak | E10: Self | F10: LivingTarget | G10: ApplyEffect | H10: effect_guard_broken | I10: 0 | J10: 0 | K10: 1 | L10: 999 | M10: 1 | N10: FIXED | O10: OPEN-WP10-08/17..20; global Self is the hook subject. | P10: =IF(AND(A10<>"",C10<>"",H10<>"",J10>=0,K10>=1,L10>=1,M10=1),"OK","ERROR") -> OK
